{
    "rankType": "5d",
    "direction": -1,
    "hasMore": true,
    "latestUpdateTime": 1630453130327,
    "data": [
        {
            "ticker": {
                "tickerId": 950053205,
                "exchangeId": 10,
                "type": 2,
                "secType": [
                    61
                ],
                "regionId": 6,
                "currencyId": 247,
                "currencyCode": "USD",
                "name": "Vinco Ventures Inc",
                "symbol": "BBIG",
                "disSymbol": "BBIG",
                "disExchangeCode": "NASDAQ",
                "exchangeCode": "NAS",
                "listStatus": 1,
                "template": "stock",
                "derivativeSupport": 1,
                "tradeTime": "2021-08-31T23:38:50.747+0000",
                "faTradeTime": "2021-08-31T23:38:50.747+0000",
                "status": "A",
                "close": "8.15",
                "change": "1.09",
                "changeRatio": "0.1544",
                "marketValue": "534350145",
                "volume": "184716171",
                "turnoverRate": "2.8180",
                "regionName": "United States",
                "regionIsoCode": "US",
                "peTtm": "-0.9224",
                "preClose": "7.06",
                "fiftyTwoWkHigh": "10.00",
                "fiftyTwoWkLow": "1.110",
                "open": "6.90",
                "high": "8.34",
                "low": "5.51",
                "vibrateRatio": "0.4009",
                "pprice": "8.19",
                "pchange": "0.04",
                "pchRatio": "0.0049"
            },
            "values": {
                "tickerId": 950053205,
                "change": "5.21",
                "changeRatio": "1.7721"
            }
        },
        {
            "ticker": {
                "tickerId": 913323870,
                "exchangeId": 10,
                "type": 2,
                "secType": [
                    61
                ],
                "regionId": 6,
                "currencyId": 247,
                "currencyCode": "USD",
                "name": "Support.com",
                "symbol": "SPRT",
                "disSymbol": "SPRT",
                "disExchangeCode": "NASDAQ",
                "exchangeCode": "NAS",
                "listStatus": 1,
                "template": "stock",
                "derivativeSupport": 1,
                "tradeTime": "2021-08-31T23:38:45.117+0000",
                "faTradeTime": "2021-08-31T23:38:45.117+0000",
                "status": "A",
                "close": "31.36",
                "change": "-5.03",
                "changeRatio": "-0.1382",
                "marketValue": "760099791",
                "volume": "28824743",
                "turnoverRate": "1.1899",
                "regionName": "United States",
                "regionIsoCode": "US",
                "peTtm": "-196.4912",
                "preClose": "36.39",
                "fiftyTwoWkHigh": "59.69",
                "fiftyTwoWkLow": "1.620",
                "open": "35.97",
                "high": "36.39",
                "low": "30.51",
                "vibrateRatio": "0.1616",
                "pprice": "31.36",
                "pchange": "0.00",
                "pchRatio": "0.0000"
            },
            "values": {
                "tickerId": 913323870,
                "change": "19.69",
                "changeRatio": "1.6872"
            }
        },
        {
            "ticker": {
                "tickerId": 950182577,
                "exchangeId": 10,
                "type": 2,
                "secType": [
                    61
                ],
                "regionId": 6,
                "currencyId": 247,
                "currencyCode": "USD",
                "name": "Regencell Bioscience Holdings Ltd",
                "symbol": "RGC",
                "disSymbol": "RGC",
                "disExchangeCode": "NASDAQ",
                "exchangeCode": "NAS",
                "listStatus": 1,
                "template": "stock",
                "tradeTime": "2021-08-31T23:13:00.037+0000",
                "faTradeTime": "2021-08-31T23:13:00.037+0000",
                "status": "A",
                "close": "34.35",
                "change": "5.47",
                "changeRatio": "0.1894",
                "marketValue": "445420056",
                "volume": "2296266",
                "turnoverRate": "0.1771",
                "regionName": "United States",
                "regionIsoCode": "US",
                "peTtm": "-511.9225",
                "preClose": "28.88",
                "fiftyTwoWkHigh": "59.00",
                "fiftyTwoWkLow": "6.00",
                "open": "29.30",
                "high": "39.53",
                "low": "28.00",
                "vibrateRatio": "0.3992",
                "pprice": "33.35",
                "pchange": "-1.00",
                "pchRatio": "-0.0291"
            },
            "values": {
                "tickerId": 950182577,
                "change": "19.05",
                "changeRatio": "1.2451"
            }
        },
        {
            "ticker": {
                "tickerId": 950102420,
                "exchangeId": 10,
                "type": 2,
                "secType": [
                    61
                ],
                "regionId": 6,
                "currencyId": 247,
                "currencyCode": "USD",
                "name": "Glory Star New Media Group Holdings Limited",
                "symbol": "GSMG",
                "disSymbol": "GSMG",
                "disExchangeCode": "NASDAQ",
                "exchangeCode": "NAS",
                "listStatus": 1,
                "template": "stock",
                "tradeTime": "2021-08-31T21:39:17.351+0000",
                "faTradeTime": "2021-08-31T21:39:17.351+0000",
                "status": "A",
                "close": "2.970",
                "change": "0.140",
                "changeRatio": "0.0495",
                "marketValue": "202323533",
                "volume": "1236710",
                "turnoverRate": "0.0182",
                "regionName": "United States",
                "regionIsoCode": "US",
                "peTtm": "5.9988",
                "preClose": "2.830",
                "fiftyTwoWkHigh": "4.860",
                "fiftyTwoWkLow": "1.280",
                "open": "2.863",
                "high": "3.020",
                "low": "2.740",
                "vibrateRatio": "0.0989",
                "pprice": "2.95",
                "pchange": "-0.020",
                "pchRatio": "-0.0067"
            },
            "values": {
                "tickerId": 950102420,
                "change": "1.490",
                "changeRatio": "1.0068"
            }
        },
        {
            "ticker": {
                "tickerId": 913324609,
                "exchangeId": 11,
                "type": 2,
                "secType": [
                    61
                ],
                "regionId": 6,
                "currencyId": 247,
                "currencyCode": "USD",
                "name": "Navios Mari",
                "symbol": "NNA",
                "disSymbol": "NNA",
                "disExchangeCode": "NYSE",
                "exchangeCode": "NYSE",
                "listStatus": 1,
                "template": "stock",
                "derivativeSupport": 1,
                "tradeTime": "2021-08-31T21:31:27.747+0000",
                "faTradeTime": "2021-08-31T21:31:27.747+0000",
                "status": "A",
                "close": "3.670",
                "change": "-0.030",
                "changeRatio": "-0.0081",
                "marketValue": "60773295",
                "volume": "749514",
                "turnoverRate": "0.0452",
                "regionName": "United States",
                "regionIsoCode": "US",
                "peTtm": "2.1322",
                "preClose": "3.700",
                "fiftyTwoWkHigh": "5.71",
                "fiftyTwoWkLow": "1.810",
                "open": "3.600",
                "high": "3.840",
                "low": "3.510",
                "vibrateRatio": "0.0892",
                "pprice": "3.74",
                "pchange": "0.070",
                "pchRatio": "0.0191"
            },
            "values": {
                "tickerId": 913324609,
                "change": "1.610",
                "changeRatio": "0.7816"
            }
        },
        {
            "ticker": {
                "tickerId": 950186087,
                "exchangeId": 95,
                "type": 2,
                "secType": [
                    61
                ],
                "regionId": 6,
                "currencyId": 247,
                "currencyCode": "USD",
                "name": "Gambling.com Group Ltd",
                "symbol": "GAMB",
                "disSymbol": "GAMB",
                "disExchangeCode": "NASDAQ",
                "exchangeCode": "NMS",
                "listStatus": 1,
                "template": "stock",
                "tradeTime": "2021-08-31T23:28:06.294+0000",
                "faTradeTime": "2021-08-31T23:28:06.294+0000",
                "status": "A",
                "close": "11.43",
                "change": "-1.35",
                "changeRatio": "-0.1056",
                "marketValue": "386407403",
                "volume": "1061384",
                "turnoverRate": "0.0314",
                "regionName": "United States",
                "regionIsoCode": "US",
                "peTtm": "0",
                "preClose": "12.78",
                "fiftyTwoWkHigh": "14.73",
                "fiftyTwoWkLow": "6.56",
                "open": "12.31",
                "high": "13.15",
                "low": "11.05",
                "vibrateRatio": "0.1620",
                "pprice": "11.57",
                "pchange": "0.14",
                "pchRatio": "0.0122"
            },
            "values": {
                "tickerId": 950186087,
                "change": "4.61",
                "changeRatio": "0.6760"
            }
        },
        {
            "ticker": {
                "tickerId": 925200020,
                "exchangeId": 12,
                "type": 2,
                "secType": [
                    61
                ],
                "regionId": 6,
                "currencyId": 247,
                "currencyCode": "USD",
                "name": "Takung Art",
                "symbol": "TKAT",
                "disSymbol": "TKAT",
                "disExchangeCode": "AMEX",
                "exchangeCode": "ASE",
                "listStatus": 1,
                "template": "stock",
                "tradeTime": "2021-08-31T23:32:17.547+0000",
                "faTradeTime": "2021-08-31T23:32:17.547+0000",
                "status": "A",
                "close": "11.68",
                "change": "1.20",
                "changeRatio": "0.1145",
                "marketValue": "136275745",
                "volume": "9550022",
                "turnoverRate": "0.8168",
                "regionName": "United States",
                "regionIsoCode": "US",
                "peTtm": "-18.1564",
                "preClose": "10.48",
                "fiftyTwoWkHigh": "74.11",
                "fiftyTwoWkLow": "0.7800",
                "open": "10.10",
                "high": "12.20",
                "low": "9.90",
                "vibrateRatio": "0.2156",
                "pprice": "11.72",
                "pchange": "0.04",
                "pchRatio": "0.0034"
            },
            "values": {
                "tickerId": 925200020,
                "change": "4.64",
                "changeRatio": "0.6591"
            }
        },
        {
            "ticker": {
                "tickerId": 925239677,
                "exchangeId": 10,
                "type": 2,
                "secType": [
                    61
                ],
                "regionId": 6,
                "currencyId": 247,
                "currencyCode": "USD",
                "name": "Elys Game Tec hnology Corp.",
                "symbol": "ELYS",
                "disSymbol": "ELYS",
                "disExchangeCode": "NASDAQ",
                "exchangeCode": "NAS",
                "listStatus": 1,
                "template": "stock",
                "derivativeSupport": 1,
                "tradeTime": "2021-08-31T23:38:13.339+0000",
                "faTradeTime": "2021-08-31T23:38:13.339+0000",
                "status": "A",
                "close": "6.62",
                "change": "1.99",
                "changeRatio": "0.4298",
                "marketValue": "154142939",
                "volume": "65941761",
                "turnoverRate": "2.8320",
                "regionName": "United States",
                "regionIsoCode": "US",
                "peTtm": "-10.8312",
                "preClose": "4.630",
                "fiftyTwoWkHigh": "8.28",
                "fiftyTwoWkLow": "1.360",
                "open": "4.580",
                "high": "6.72",
                "low": "4.580",
                "vibrateRatio": "0.4600",
                "pprice": "6.42",
                "pchange": "-0.20",
                "pchRatio": "-0.0302"
            },
            "values": {
                "tickerId": 925239677,
                "change": "2.57",
                "changeRatio": "0.6346"
            }
        },
        {
            "ticker": {
                "tickerId": 950126090,
                "exchangeId": 10,
                "type": 2,
                "secType": [
                    61
                ],
                "regionId": 6,
                "currencyId": 247,
                "currencyCode": "USD",
                "name": "Aterian Inc",
                "symbol": "ATER",
                "disSymbol": "ATER",
                "disExchangeCode": "NASDAQ",
                "exchangeCode": "NAS",
                "listStatus": 1,
                "template": "stock",
                "derivativeSupport": 1,
                "tradeTime": "2021-08-31T23:33:27.060+0000",
                "faTradeTime": "2021-08-31T23:33:27.060+0000",
                "status": "A",
                "close": "5.96",
                "change": "-0.66",
                "changeRatio": "-0.0997",
                "marketValue": "212979211",
                "volume": "15158212",
                "turnoverRate": "0.4243",
                "regionName": "United States",
                "regionIsoCode": "US",
                "peTtm": "-0.9114",
                "preClose": "6.62",
                "fiftyTwoWkHigh": "48.99",
                "fiftyTwoWkLow": "3.040",
                "open": "6.41",
                "high": "6.44",
                "low": "5.32",
                "vibrateRatio": "0.1692",
                "pprice": "5.73",
                "pchange": "-0.23",
                "pchRatio": "-0.0386"
            },
            "values": {
                "tickerId": 950126090,
                "change": "2.22",
                "changeRatio": "0.5936"
            }
        },
        {
            "ticker": {
                "tickerId": 913303704,
                "exchangeId": 12,
                "type": 2,
                "secType": [
                    61
                ],
                "regionId": 6,
                "currencyId": 247,
                "currencyCode": "USD",
                "name": "ALTISOURCE ASSET",
                "symbol": "AAMC",
                "disSymbol": "AAMC",
                "disExchangeCode": "AMEX",
                "exchangeCode": "ASE",
                "listStatus": 1,
                "template": "stock",
                "tradeTime": "2021-08-31T22:13:41.483+0000",
                "faTradeTime": "2021-08-31T22:13:41.483+0000",
                "status": "A",
                "close": "21.70",
                "change": "3.95",
                "changeRatio": "0.2225",
                "marketValue": "44605673",
                "volume": "1015366",
                "turnoverRate": "0.4938",
                "regionName": "United States",
                "regionIsoCode": "US",
                "peTtm": "0.6009",
                "preClose": "17.75",
                "fiftyTwoWkHigh": "31.24",
                "fiftyTwoWkLow": "12.54",
                "open": "17.71",
                "high": "27.00",
                "low": "16.83",
                "vibrateRatio": "0.5730",
                "pprice": "21.70",
                "pchange": "0.00",
                "pchRatio": "0.0000"
            },
            "values": {
                "tickerId": 913303704,
                "change": "8.03",
                "changeRatio": "0.5874"
            }
        },
        {
            "ticker": {
                "tickerId": 913255912,
                "exchangeId": 10,
                "type": 2,
                "secType": [
                    61
                ],
                "regionId": 6,
                "currencyId": 247,
                "currencyCode": "USD",
                "name": "Sphere 3D",
                "symbol": "ANY",
                "disSymbol": "ANY",
                "disExchangeCode": "NASDAQ",
                "exchangeCode": "NAS",
                "listStatus": 1,
                "template": "stock",
                "derivativeSupport": 1,
                "tradeTime": "2021-08-31T23:38:00.122+0000",
                "faTradeTime": "2021-08-31T23:38:00.122+0000",
                "status": "A",
                "close": "6.49",
                "change": "0.09",
                "changeRatio": "0.0141",
                "marketValue": "146557368",
                "volume": "17761892",
                "turnoverRate": "0.7866",
                "regionName": "United States",
                "regionIsoCode": "US",
                "peTtm": "-7.8080",
                "preClose": "6.40",
                "fiftyTwoWkHigh": "7.68",
                "fiftyTwoWkLow": "1.230",
                "open": "6.05",
                "high": "6.75",
                "low": "5.53",
                "vibrateRatio": "0.1891",
                "pprice": "6.48",
                "pchange": "-0.01",
                "pchRatio": "-0.0015"
            },
            "values": {
                "tickerId": 913255912,
                "change": "2.39",
                "changeRatio": "0.5829"
            }
        },
        {
            "ticker": {
                "tickerId": 950177471,
                "exchangeId": 10,
                "type": 2,
                "secType": [
                    61
                ],
                "regionId": 6,
                "currencyId": 247,
                "currencyCode": "USD",
                "name": "Vallon Pharmaceuticals, Inc.",
                "symbol": "VLON",
                "disSymbol": "VLON",
                "disExchangeCode": "NASDAQ",
                "exchangeCode": "NAS",
                "listStatus": 1,
                "template": "stock",
                "tradeTime": "2021-08-31T23:24:45.657+0000",
                "faTradeTime": "2021-08-31T23:24:45.657+0000",
                "status": "A",
                "close": "7.03",
                "change": "1.36",
                "changeRatio": "0.2399",
                "marketValue": "43418798",
                "volume": "5168991",
                "turnoverRate": "0.8372",
                "regionName": "United States",
                "regionIsoCode": "US",
                "peTtm": "-6.0261",
                "preClose": "5.67",
                "fiftyTwoWkHigh": "9.90",
                "fiftyTwoWkLow": "3.610",
                "open": "5.71",
                "high": "8.20",
                "low": "5.71",
                "vibrateRatio": "0.4392",
                "pprice": "7.30",
                "pchange": "0.27",
                "pchRatio": "0.0384"
            },
            "values": {
                "tickerId": 950177471,
                "change": "2.56",
                "changeRatio": "0.5727"
            }
        },
        {
            "ticker": {
                "tickerId": 913303719,
                "exchangeId": 12,
                "type": 2,
                "secType": [
                    61
                ],
                "regionId": 6,
                "currencyId": 247,
                "currencyCode": "USD",
                "name": "GLOBALSTAR",
                "symbol": "GSAT",
                "disSymbol": "GSAT",
                "disExchangeCode": "AMEX",
                "exchangeCode": "ASE",
                "listStatus": 1,
                "template": "stock",
                "derivativeSupport": 1,
                "tradeTime": "2021-08-31T23:36:23.140+0000",
                "faTradeTime": "2021-08-31T23:36:23.140+0000",
                "status": "A",
                "close": "1.990",
                "change": "-0.360",
                "changeRatio": "-0.1532",
                "marketValue": "3568070000",
                "volume": "147622859",
                "turnoverRate": "0.0820",
                "regionName": "United States",
                "regionIsoCode": "US",
                "peTtm": "-32.3577",
                "preClose": "2.350",
                "fiftyTwoWkHigh": "2.980",
                "fiftyTwoWkLow": "0.2920",
                "open": "2.020",
                "high": "2.150",
                "low": "1.860",
                "vibrateRatio": "0.1234",
                "pprice": "1.98",
                "pchange": "-0.010",
                "pchRatio": "-0.0050"
            },
            "values": {
                "tickerId": 913303719,
                "change": "0.670",
                "changeRatio": "0.5076"
            }
        },
        {
            "ticker": {
                "tickerId": 950182515,
                "exchangeId": 95,
                "type": 2,
                "secType": [
                    61
                ],
                "regionId": 6,
                "currencyId": 247,
                "currencyCode": "USD",
                "name": "Reneo Pharmaceuticals, Inc.",
                "symbol": "RPHM",
                "disSymbol": "RPHM",
                "disExchangeCode": "NASDAQ",
                "exchangeCode": "NMS",
                "listStatus": 1,
                "template": "stock",
                "tradeTime": "2021-08-31T21:47:22.452+0000",
                "faTradeTime": "2021-08-31T21:47:22.452+0000",
                "status": "A",
                "close": "11.07",
                "change": "1.61",
                "changeRatio": "0.1702",
                "marketValue": "270166969",
                "volume": "570802",
                "turnoverRate": "0.0234",
                "regionName": "United States",
                "regionIsoCode": "US",
                "peTtm": "-13.7687",
                "preClose": "9.46",
                "fiftyTwoWkHigh": "17.18",
                "fiftyTwoWkLow": "6.10",
                "open": "9.74",
                "high": "11.40",
                "low": "9.63",
                "vibrateRatio": "0.1807",
                "pprice": "11.19",
                "pchange": "0.12",
                "pchRatio": "0.0108"
            },
            "values": {
                "tickerId": 950182515,
                "change": "3.68",
                "changeRatio": "0.4980"
            }
        },
        {
            "ticker": {
                "tickerId": 913254020,
                "exchangeId": 10,
                "type": 2,
                "secType": [
                    61
                ],
                "regionId": 6,
                "currencyId": 247,
                "currencyCode": "USD",
                "name": "Live Ventures",
                "symbol": "LIVE",
                "disSymbol": "LIVE",
                "disExchangeCode": "NASDAQ",
                "exchangeCode": "NAS",
                "listStatus": 1,
                "template": "stock",
                "tradeTime": "2021-08-31T21:28:57.517+0000",
                "faTradeTime": "2021-08-31T21:28:57.517+0000",
                "status": "A",
                "close": "44.81",
                "change": "6.03",
                "changeRatio": "0.1555",
                "marketValue": "70389071",
                "volume": "91036",
                "turnoverRate": "0.0580",
                "regionName": "United States",
                "regionIsoCode": "US",
                "peTtm": "5.2843",
                "preClose": "38.78",
                "fiftyTwoWkHigh": "75.25",
                "fiftyTwoWkLow": "7.83",
                "open": "39.01",
                "high": "46.95",
                "low": "39.01",
                "vibrateRatio": "0.2047",
                "pprice": "45.72",
                "pchange": "0.91",
                "pchRatio": "0.0203"
            },
            "values": {
                "tickerId": 913254020,
                "change": "14.54",
                "changeRatio": "0.4803"
            }
        },
        {
            "ticker": {
                "tickerId": 950183434,
                "exchangeId": 96,
                "type": 2,
                "secType": [
                    62
                ],
                "regionId": 6,
                "currencyId": 247,
                "currencyCode": "USD",
                "name": "Valneva SE",
                "symbol": "VALN",
                "disSymbol": "VALN",
                "disExchangeCode": "NASDAQ",
                "exchangeCode": "NSQ",
                "listStatus": 1,
                "template": "stock",
                "tradeTime": "2021-08-31T23:08:46.948+0000",
                "faTradeTime": "2021-08-31T23:08:46.948+0000",
                "status": "A",
                "close": "53.00",
                "change": "2.00",
                "changeRatio": "0.0392",
                "marketValue": "2643709324",
                "volume": "194313",
                "turnoverRate": "0.0039",
                "regionName": "United States",
                "regionIsoCode": "US",
                "peTtm": "-16.6976",
                "preClose": "51.00",
                "fiftyTwoWkHigh": "59.15",
                "fiftyTwoWkLow": "24.16",
                "open": "53.31",
                "high": "53.70",
                "low": "47.93",
                "vibrateRatio": "0.1041",
                "pprice": "53.40",
                "pchange": "0.40",
                "pchRatio": "0.0075"
            },
            "values": {
                "tickerId": 950183434,
                "change": "17.00",
                "changeRatio": "0.4722"
            }
        },
        {
            "ticker": {
                "tickerId": 950177898,
                "exchangeId": 10,
                "type": 2,
                "secType": [
                    61
                ],
                "regionId": 6,
                "currencyId": 247,
                "currencyCode": "USD",
                "name": "ALPHA HEALTHCARE",
                "symbol": "HUMA",
                "disSymbol": "HUMA",
                "disExchangeCode": "NASDAQ",
                "exchangeCode": "NAS",
                "listStatus": 1,
                "template": "stock",
                "derivativeSupport": 1,
                "tradeTime": "2021-08-31T23:35:08.106+0000",
                "faTradeTime": "2021-08-31T23:35:08.106+0000",
                "status": "A",
                "close": "14.62",
                "change": "1.32",
                "changeRatio": "0.0992",
                "marketValue": "187940100",
                "volume": "605244",
                "turnoverRate": "0.0471",
                "regionName": "United States",
                "regionIsoCode": "US",
                "peTtm": "-803.2967",
                "preClose": "13.30",
                "fiftyTwoWkHigh": "16.96",
                "fiftyTwoWkLow": "9.12",
                "open": "13.50",
                "high": "15.22",
                "low": "13.48",
                "vibrateRatio": "0.1293",
                "pprice": "14.31",
                "pchange": "-0.31",
                "pchRatio": "-0.0212"
            },
            "values": {
                "tickerId": 950177898,
                "change": "4.52",
                "changeRatio": "0.4475"
            }
        },
        {
            "ticker": {
                "tickerId": 913254265,
                "exchangeId": 10,
                "type": 2,
                "secType": [
                    61
                ],
                "regionId": 6,
                "currencyId": 247,
                "currencyCode": "USD",
                "name": "CREG",
                "symbol": "CREG",
                "disSymbol": "CREG",
                "disExchangeCode": "NASDAQ",
                "exchangeCode": "NAS",
                "listStatus": 1,
                "template": "stock",
                "tradeTime": "2021-08-31T23:28:51.286+0000",
                "faTradeTime": "2021-08-31T23:28:51.286+0000",
                "status": "A",
                "close": "9.16",
                "change": "0.71",
                "changeRatio": "0.0840",
                "marketValue": "60303275",
                "volume": "229319",
                "turnoverRate": "0.0348",
                "regionName": "United States",
                "regionIsoCode": "US",
                "peTtm": "6.3505",
                "preClose": "8.45",
                "fiftyTwoWkHigh": "14.39",
                "fiftyTwoWkLow": "2.160",
                "open": "8.24",
                "high": "9.17",
                "low": "7.89",
                "vibrateRatio": "0.1515",
                "pprice": "9.15",
                "pchange": "-0.01",
                "pchRatio": "-0.0011"
            },
            "values": {
                "tickerId": 913254265,
                "change": "2.80",
                "changeRatio": "0.4403"
            }
        },
        {
            "ticker": {
                "tickerId": 950185444,
                "exchangeId": 95,
                "type": 2,
                "secType": [
                    61
                ],
                "regionId": 6,
                "currencyId": 247,
                "currencyCode": "USD",
                "name": "Aerovate Therapeutics, Inc.",
                "symbol": "AVTE",
                "disSymbol": "AVTE",
                "disExchangeCode": "NASDAQ",
                "exchangeCode": "NMS",
                "listStatus": 1,
                "template": "stock",
                "tradeTime": "2021-08-31T20:00:00.000+0000",
                "faTradeTime": "2021-08-31T13:00:35.243+0000",
                "status": "D",
                "close": "17.09",
                "change": "0.21",
                "changeRatio": "0.0124",
                "marketValue": "417173616",
                "volume": "62658",
                "turnoverRate": "0.0026",
                "regionName": "United States",
                "regionIsoCode": "US",
                "peTtm": "-35.5080",
                "preClose": "16.88",
                "fiftyTwoWkHigh": "29.43",
                "fiftyTwoWkLow": "11.40",
                "open": "17.04",
                "high": "19.00",
                "low": "15.62",
                "vibrateRatio": "0.2002",
                "pprice": "16.00",
                "pchange": "-0.88",
                "pchRatio": "-0.0521"
            },
            "values": {
                "tickerId": 950185444,
                "change": "5.09",
                "changeRatio": "0.4242"
            }
        },
        {
            "ticker": {
                "tickerId": 950178219,
                "exchangeId": 96,
                "type": 2,
                "secType": [
                    61
                ],
                "regionId": 6,
                "currencyId": 247,
                "currencyCode": "USD",
                "name": "Affirm Holdings, Inc.",
                "symbol": "AFRM",
                "disSymbol": "AFRM",
                "disExchangeCode": "NASDAQ",
                "exchangeCode": "NSQ",
                "listStatus": 1,
                "template": "stock",
                "derivativeSupport": 1,
                "tradeTime": "2021-08-31T23:36:20.825+0000",
                "faTradeTime": "2021-08-31T23:36:20.825+0000",
                "status": "A",
                "close": "96.34",
                "change": "-3.25",
                "changeRatio": "-0.0326",
                "marketValue": "23386223918",
                "volume": "15814854",
                "turnoverRate": "0.0652",
                "regionName": "United States",
                "regionIsoCode": "US",
                "peTtm": "-92.4746",
                "preClose": "99.59",
                "fiftyTwoWkHigh": "146.90",
                "fiftyTwoWkLow": "46.50",
                "open": "95.24",
                "high": "96.55",
                "low": "90.28",
                "vibrateRatio": "0.0630",
                "pprice": "95.80",
                "pchange": "-0.54",
                "pchRatio": "-0.0056"
            },
            "values": {
                "tickerId": 950178219,
                "change": "27.81",
                "changeRatio": "0.4058"
            }
        },
        {
            "ticker": {
                "tickerId": 950108254,
                "exchangeId": 10,
                "type": 2,
                "secType": [
                    61
                ],
                "regionId": 6,
                "currencyId": 247,
                "currencyCode": "USD",
                "name": "ASIA TIMES HOLDINGS LTD",
                "symbol": "ATIF",
                "disSymbol": "ATIF",
                "disExchangeCode": "NASDAQ",
                "exchangeCode": "NAS",
                "listStatus": 1,
                "template": "stock",
                "tradeTime": "2021-08-31T23:36:17.853+0000",
                "faTradeTime": "2021-08-31T23:36:17.853+0000",
                "status": "A",
                "close": "3.430",
                "change": "0.050",
                "changeRatio": "0.0148",
                "marketValue": "31423571",
                "volume": "2435407",
                "turnoverRate": "0.2659",
                "regionName": "United States",
                "regionIsoCode": "US",
                "peTtm": "-9.5119",
                "preClose": "3.380",
                "fiftyTwoWkHigh": "11.70",
                "fiftyTwoWkLow": "2.105",
                "open": "3.162",
                "high": "3.746",
                "low": "2.860",
                "vibrateRatio": "0.2604",
                "pprice": "3.34",
                "pchange": "-0.090",
                "pchRatio": "-0.0262"
            },
            "values": {
                "tickerId": 950108254,
                "change": "0.990",
                "changeRatio": "0.4057"
            }
        },
        {
            "ticker": {
                "tickerId": 925300251,
                "exchangeId": 95,
                "type": 2,
                "secType": [
                    61
                ],
                "regionId": 6,
                "currencyId": 247,
                "currencyCode": "USD",
                "name": "Bragg Gaming Group Inc",
                "symbol": "BRAG",
                "disSymbol": "BRAG",
                "disExchangeCode": "NASDAQ",
                "exchangeCode": "NMS",
                "listStatus": 1,
                "template": "stock",
                "tradeTime": "2021-08-31T20:00:00.000+0000",
                "faTradeTime": "2021-08-31T13:16:41.548+0000",
                "status": "D",
                "close": "12.27",
                "change": "1.15",
                "changeRatio": "0.1034",
                "marketValue": "243238197",
                "volume": "219817",
                "turnoverRate": "0.0111",
                "regionName": "United States",
                "regionIsoCode": "US",
                "peTtm": "-9.5576",
                "preClose": "11.12",
                "fiftyTwoWkHigh": "25.01",
                "fiftyTwoWkLow": "2.830",
                "open": "11.19",
                "high": "12.27",
                "low": "10.82",
                "vibrateRatio": "0.1241",
                "pprice": "11.15",
                "pchange": "0.03",
                "pchRatio": "0.0027"
            },
            "values": {
                "tickerId": 925300251,
                "change": "3.52",
                "changeRatio": "0.4023"
            }
        },
        {
            "ticker": {
                "tickerId": 913323825,
                "exchangeId": 95,
                "type": 2,
                "secType": [
                    61
                ],
                "regionId": 6,
                "currencyId": 247,
                "currencyCode": "USD",
                "name": "Unico American",
                "symbol": "UNAM",
                "disSymbol": "UNAM",
                "disExchangeCode": "NASDAQ",
                "exchangeCode": "NMS",
                "listStatus": 1,
                "template": "stock",
                "tradeTime": "2021-08-31T23:37:01.352+0000",
                "faTradeTime": "2021-08-31T23:37:01.352+0000",
                "status": "A",
                "close": "4.150",
                "change": "1.540",
                "changeRatio": "0.5900",
                "marketValue": "22015181",
                "volume": "5061875",
                "turnoverRate": "0.9620",
                "regionName": "United States",
                "regionIsoCode": "US",
                "peTtm": "-1.1497",
                "preClose": "2.610",
                "fiftyTwoWkHigh": "8.60",
                "fiftyTwoWkLow": "2.533",
                "open": "2.870",
                "high": "4.720",
                "low": "2.750",
                "vibrateRatio": "0.7546",
                "pprice": "4.59",
                "pchange": "0.440",
                "pchRatio": "0.1060"
            },
            "values": {
                "tickerId": 913323825,
                "change": "1.190",
                "changeRatio": "0.4020"
            }
        },
        {
            "ticker": {
                "tickerId": 913324149,
                "exchangeId": 95,
                "type": 2,
                "secType": [
                    61
                ],
                "regionId": 6,
                "currencyId": 247,
                "currencyCode": "USD",
                "name": "Pixelworks",
                "symbol": "PXLW",
                "disSymbol": "PXLW",
                "disExchangeCode": "NASDAQ",
                "exchangeCode": "NMS",
                "listStatus": 1,
                "template": "stock",
                "derivativeSupport": 1,
                "tradeTime": "2021-08-31T23:37:39.914+0000",
                "faTradeTime": "2021-08-31T23:37:39.914+0000",
                "status": "A",
                "close": "7.75",
                "change": "1.53",
                "changeRatio": "0.2460",
                "marketValue": "406365181",
                "volume": "8787610",
                "turnoverRate": "0.1676",
                "regionName": "United States",
                "regionIsoCode": "US",
                "peTtm": "-13.2050",
                "preClose": "6.22",
                "fiftyTwoWkHigh": "7.56",
                "fiftyTwoWkLow": "1.847",
                "open": "6.46",
                "high": "7.90",
                "low": "6.31",
                "vibrateRatio": "0.2508",
                "pprice": "7.96",
                "pchange": "0.21",
                "pchRatio": "0.0271"
            },
            "values": {
                "tickerId": 913324149,
                "change": "2.20",
                "changeRatio": "0.3964"
            }
        },
        {
            "ticker": {
                "tickerId": 925377021,
                "exchangeId": 12,
                "type": 2,
                "secType": [
                    61
                ],
                "regionId": 6,
                "currencyId": 247,
                "currencyCode": "USD",
                "name": "Regional Health",
                "symbol": "RHE",
                "disSymbol": "RHE",
                "disExchangeCode": "AMEX",
                "exchangeCode": "ASE",
                "listStatus": 1,
                "template": "stock",
                "tradeTime": "2021-08-31T23:37:21.176+0000",
                "faTradeTime": "2021-08-31T23:37:21.176+0000",
                "status": "A",
                "close": "11.19",
                "change": "2.88",
                "changeRatio": "0.3466",
                "marketValue": "19320709",
                "volume": "50259197",
                "turnoverRate": "29.0890",
                "regionName": "United States",
                "regionIsoCode": "US",
                "peTtm": "-1.8123",
                "preClose": "8.31",
                "fiftyTwoWkHigh": "27.72",
                "fiftyTwoWkLow": "1.126",
                "open": "10.50",
                "high": "13.90",
                "low": "10.36",
                "vibrateRatio": "0.4256",
                "pprice": "10.97",
                "pchange": "-0.22",
                "pchRatio": "-0.0197"
            },
            "values": {
                "tickerId": 925377021,
                "change": "3.01",
                "changeRatio": "0.3680"
            }
        },
        {
            "ticker": {
                "tickerId": 913323355,
                "exchangeId": 11,
                "type": 2,
                "secType": [
                    62
                ],
                "regionId": 6,
                "currencyId": 247,
                "currencyCode": "USD",
                "name": "Edenor",
                "symbol": "EDN",
                "disSymbol": "EDN",
                "disExchangeCode": "NYSE",
                "exchangeCode": "NYSE",
                "listStatus": 1,
                "template": "stock",
                "tradeTime": "2021-08-31T20:00:00.000+0000",
                "faTradeTime": "2021-08-31T13:30:04.357+0000",
                "status": "D",
                "close": "7.24",
                "change": "-0.21",
                "changeRatio": "-0.0282",
                "marketValue": "160080157",
                "volume": "185747",
                "turnoverRate": "0.0084",
                "regionName": "United States",
                "regionIsoCode": "US",
                "peTtm": "-1.1116",
                "preClose": "7.45",
                "fiftyTwoWkHigh": "7.79",
                "fiftyTwoWkLow": "2.811",
                "open": "7.45",
                "high": "7.90",
                "low": "6.84",
                "vibrateRatio": "0.1417",
                "pprice": "7.0904",
                "pchange": "-0.36",
                "pchRatio": "-0.0483"
            },
            "values": {
                "tickerId": 913323355,
                "change": "1.94",
                "changeRatio": "0.3660"
            }
        },
        {
            "ticker": {
                "tickerId": 950151234,
                "exchangeId": 95,
                "type": 2,
                "secType": [
                    61
                ],
                "regionId": 6,
                "currencyId": 247,
                "currencyCode": "USD",
                "name": "Katapult Holdings Inc",
                "symbol": "KPLT",
                "disSymbol": "KPLT",
                "disExchangeCode": "NASDAQ",
                "exchangeCode": "NMS",
                "listStatus": 1,
                "template": "stock",
                "derivativeSupport": 1,
                "tradeTime": "2021-08-31T23:35:16.039+0000",
                "faTradeTime": "2021-08-31T23:35:16.039+0000",
                "status": "A",
                "close": "4.845",
                "change": "-0.245",
                "changeRatio": "-0.0481",
                "marketValue": "469100724",
                "volume": "15577909",
                "turnoverRate": "0.1609",
                "regionName": "United States",
                "regionIsoCode": "US",
                "peTtm": "-4.8421",
                "preClose": "5.09",
                "fiftyTwoWkHigh": "19.65",
                "fiftyTwoWkLow": "3.100",
                "open": "4.750",
                "high": "5.08",
                "low": "4.410",
                "vibrateRatio": "0.1297",
                "pprice": "4.77",
                "pchange": "-0.075",
                "pchRatio": "-0.0155"
            },
            "values": {
                "tickerId": 950151234,
                "change": "1.295",
                "changeRatio": "0.3648"
            }
        },
        {
            "ticker": {
                "tickerId": 913253355,
                "exchangeId": 10,
                "type": 2,
                "secType": [
                    61
                ],
                "regionId": 6,
                "currencyId": 247,
                "currencyCode": "USD",
                "name": "SGOCO",
                "symbol": "SGOC",
                "disSymbol": "SGOC",
                "disExchangeCode": "NASDAQ",
                "exchangeCode": "NAS",
                "listStatus": 1,
                "template": "stock",
                "derivativeSupport": 1,
                "tradeTime": "2021-08-31T23:28:36.696+0000",
                "faTradeTime": "2021-08-31T23:28:36.696+0000",
                "status": "A",
                "close": "8.27",
                "change": "0.04",
                "changeRatio": "0.0049",
                "marketValue": "840215443",
                "volume": "1844549",
                "turnoverRate": "0.0182",
                "regionName": "United States",
                "regionIsoCode": "US",
                "peTtm": "-12.2628",
                "preClose": "8.23",
                "fiftyTwoWkHigh": "29.00",
                "fiftyTwoWkLow": "0.7700",
                "open": "8.08",
                "high": "8.55",
                "low": "7.80",
                "vibrateRatio": "0.0911",
                "pprice": "8.26",
                "pchange": "-0.01",
                "pchRatio": "-0.0012"
            },
            "values": {
                "tickerId": 913253355,
                "change": "2.19",
                "changeRatio": "0.3602"
            }
        },
        {
            "ticker": {
                "tickerId": 950159848,
                "exchangeId": 11,
                "type": 2,
                "secType": [
                    61
                ],
                "regionId": 6,
                "currencyId": 247,
                "currencyCode": "USD",
                "name": "IronNet Inc",
                "symbol": "IRNT",
                "disSymbol": "IRNT",
                "disExchangeCode": "NYSE",
                "exchangeCode": "NYSE",
                "listStatus": 1,
                "template": "stock",
                "derivativeSupport": 1,
                "tradeTime": "2021-08-31T23:20:50.087+0000",
                "faTradeTime": "2021-08-31T23:20:50.087+0000",
                "status": "A",
                "close": "13.43",
                "change": "-0.57",
                "changeRatio": "-0.0407",
                "marketValue": "289584375",
                "volume": "936867",
                "turnoverRate": "0.0434",
                "regionName": "United States",
                "regionIsoCode": "US",
                "peTtm": "-20.4663",
                "preClose": "14.00",
                "fiftyTwoWkHigh": "18.41",
                "fiftyTwoWkLow": "9.37",
                "open": "13.77",
                "high": "14.04",
                "low": "13.04",
                "vibrateRatio": "0.0714",
                "pprice": "13.50",
                "pchange": "0.07",
                "pchRatio": "0.0052"
            },
            "values": {
                "tickerId": 950159848,
                "change": "3.54",
                "changeRatio": "0.3579"
            }
        },
        {
            "ticker": {
                "tickerId": 913256080,
                "exchangeId": 10,
                "type": 2,
                "secType": [
                    61
                ],
                "regionId": 6,
                "currencyId": 247,
                "currencyCode": "USD",
                "name": "Ferroglobe",
                "symbol": "GSM",
                "disSymbol": "GSM",
                "disExchangeCode": "NASDAQ",
                "exchangeCode": "NAS",
                "listStatus": 1,
                "template": "stock",
                "derivativeSupport": 1,
                "tradeTime": "2021-08-31T22:38:25.468+0000",
                "faTradeTime": "2021-08-31T22:38:25.468+0000",
                "status": "A",
                "close": "8.31",
                "change": "0.64",
                "changeRatio": "0.0834",
                "marketValue": "1480199803",
                "volume": "4152282",
                "turnoverRate": "0.0233",
                "regionName": "United States",
                "regionIsoCode": "US",
                "peTtm": "-5.7090",
                "preClose": "7.67",
                "fiftyTwoWkHigh": "8.05",
                "fiftyTwoWkLow": "0.4040",
                "open": "7.75",
                "high": "8.36",
                "low": "7.73",
                "vibrateRatio": "0.0821",
                "pprice": "8.31",
                "pchange": "0.00",
                "pchRatio": "0.0000"
            },
            "values": {
                "tickerId": 913256080,
                "change": "2.16",
                "changeRatio": "0.3512"
            }
        },
        {
            "ticker": {
                "tickerId": 950169872,
                "exchangeId": 95,
                "type": 2,
                "secType": [
                    61
                ],
                "regionId": 6,
                "currencyId": 247,
                "currencyCode": "USD",
                "name": "Gemini Therapeutics, Inc.",
                "symbol": "GMTX",
                "disSymbol": "GMTX",
                "disExchangeCode": "NASDAQ",
                "exchangeCode": "NMS",
                "listStatus": 1,
                "template": "stock",
                "derivativeSupport": 1,
                "tradeTime": "2021-08-31T21:59:19.162+0000",
                "faTradeTime": "2021-08-31T21:59:19.162+0000",
                "status": "A",
                "close": "4.920",
                "change": "0.850",
                "changeRatio": "0.2088",
                "marketValue": "212098602",
                "volume": "1695604",
                "turnoverRate": "0.0393",
                "regionName": "United States",
                "regionIsoCode": "US",
                "peTtm": "-4.7403",
                "preClose": "4.070",
                "fiftyTwoWkHigh": "19.09",
                "fiftyTwoWkLow": "3.220",
                "open": "4.090",
                "high": "4.960",
                "low": "4.048",
                "vibrateRatio": "0.2133",
                "pprice": "4.93",
                "pchange": "0.010",
                "pchRatio": "0.0020"
            },
            "values": {
                "tickerId": 950169872,
                "change": "1.270",
                "changeRatio": "0.3479"
            }
        },
        {
            "ticker": {
                "tickerId": 950183495,
                "exchangeId": 96,
                "type": 2,
                "secType": [
                    61
                ],
                "regionId": 6,
                "currencyId": 247,
                "currencyCode": "USD",
                "name": "TaskUs, Inc.",
                "symbol": "TASK",
                "disSymbol": "TASK",
                "disExchangeCode": "NASDAQ",
                "exchangeCode": "NSQ",
                "listStatus": 1,
                "template": "stock",
                "tradeTime": "2021-08-31T21:34:00.279+0000",
                "faTradeTime": "2021-08-31T21:34:00.279+0000",
                "status": "A",
                "close": "62.90",
                "change": "4.05",
                "changeRatio": "0.0688",
                "marketValue": "6119551944",
                "volume": "1013474",
                "turnoverRate": "0.0104",
                "regionName": "United States",
                "regionIsoCode": "US",
                "peTtm": "177.1831",
                "preClose": "58.85",
                "fiftyTwoWkHigh": "59.85",
                "fiftyTwoWkLow": "26.66",
                "open": "59.56",
                "high": "63.95",
                "low": "57.58",
                "vibrateRatio": "0.1082",
                "pprice": "62.30",
                "pchange": "-0.60",
                "pchRatio": "-0.0095"
            },
            "values": {
                "tickerId": 950183495,
                "change": "16.15",
                "changeRatio": "0.3455"
            }
        },
        {
            "ticker": {
                "tickerId": 913255828,
                "exchangeId": 10,
                "type": 2,
                "secType": [
                    61
                ],
                "regionId": 6,
                "currencyId": 247,
                "currencyCode": "USD",
                "name": "Enlivex Therapeutics Ltd",
                "symbol": "ENLV",
                "disSymbol": "ENLV",
                "disExchangeCode": "NASDAQ",
                "exchangeCode": "NAS",
                "listStatus": 1,
                "template": "stock",
                "derivativeSupport": 1,
                "tradeTime": "2021-08-31T22:51:50.829+0000",
                "faTradeTime": "2021-08-31T22:51:50.829+0000",
                "status": "A",
                "close": "13.86",
                "change": "1.79",
                "changeRatio": "0.1483",
                "marketValue": "253723737",
                "volume": "542743",
                "turnoverRate": "0.0296",
                "regionName": "United States",
                "regionIsoCode": "US",
                "peTtm": "-14.9032",
                "preClose": "12.07",
                "fiftyTwoWkHigh": "29.40",
                "fiftyTwoWkLow": "4.580",
                "open": "12.14",
                "high": "13.95",
                "low": "12.05",
                "vibrateRatio": "0.1574",
                "pprice": "13.92",
                "pchange": "0.06",
                "pchRatio": "0.0043"
            },
            "values": {
                "tickerId": 913255828,
                "change": "3.52",
                "changeRatio": "0.3404"
            }
        },
        {
            "ticker": {
                "tickerId": 913255824,
                "exchangeId": 95,
                "type": 2,
                "secType": [
                    61
                ],
                "regionId": 6,
                "currencyId": 247,
                "currencyCode": "USD",
                "name": "Neoleukin Therapeutics",
                "symbol": "NLTX",
                "disSymbol": "NLTX",
                "disExchangeCode": "NASDAQ",
                "exchangeCode": "NMS",
                "listStatus": 1,
                "template": "stock",
                "derivativeSupport": 1,
                "tradeTime": "2021-08-31T20:41:37.106+0000",
                "faTradeTime": "2021-08-31T20:41:37.106+0000",
                "status": "A",
                "close": "8.15",
                "change": "0.02",
                "changeRatio": "0.0025",
                "marketValue": "345764328",
                "volume": "208810",
                "turnoverRate": "0.0049",
                "regionName": "United States",
                "regionIsoCode": "US",
                "peTtm": "-9.9390",
                "preClose": "8.13",
                "fiftyTwoWkHigh": "17.95",
                "fiftyTwoWkLow": "5.95",
                "open": "8.08",
                "high": "8.17",
                "low": "7.93",
                "vibrateRatio": "0.0295",
                "pprice": "8.15",
                "pchange": "0.00",
                "pchRatio": "0.0000"
            },
            "values": {
                "tickerId": 913255824,
                "change": "2.05",
                "changeRatio": "0.3361"
            }
        },
        {
            "ticker": {
                "tickerId": 913303936,
                "exchangeId": 95,
                "type": 2,
                "secType": [
                    62
                ],
                "regionId": 6,
                "currencyId": 247,
                "currencyCode": "USD",
                "name": "Redhill Biopharm",
                "symbol": "RDHL",
                "disSymbol": "RDHL",
                "disExchangeCode": "NASDAQ",
                "exchangeCode": "NMS",
                "listStatus": 1,
                "template": "stock",
                "derivativeSupport": 1,
                "tradeTime": "2021-08-31T23:37:22.397+0000",
                "faTradeTime": "2021-08-31T23:37:22.397+0000",
                "status": "A",
                "close": "10.10",
                "change": "1.51",
                "changeRatio": "0.1758",
                "marketValue": "471872131",
                "volume": "9840232",
                "turnoverRate": "0.2106",
                "regionName": "United States",
                "regionIsoCode": "US",
                "peTtm": "-4.3951",
                "preClose": "8.59",
                "fiftyTwoWkHigh": "11.52",
                "fiftyTwoWkLow": "5.90",
                "open": "9.04",
                "high": "11.18",
                "low": "9.04",
                "vibrateRatio": "0.2491",
                "pprice": "10.05",
                "pchange": "-0.05",
                "pchRatio": "-0.0050"
            },
            "values": {
                "tickerId": 913303936,
                "change": "2.51",
                "changeRatio": "0.3307"
            }
        },
        {
            "ticker": {
                "tickerId": 950173651,
                "exchangeId": 10,
                "type": 2,
                "secType": [
                    61
                ],
                "regionId": 6,
                "currencyId": 247,
                "currencyCode": "USD",
                "name": "Huadi International Group Co., Ltd.",
                "symbol": "HUDI",
                "disSymbol": "HUDI",
                "disExchangeCode": "NASDAQ",
                "exchangeCode": "NAS",
                "listStatus": 1,
                "template": "stock",
                "tradeTime": "2021-08-31T20:00:00.000+0000",
                "status": "D",
                "close": "4.090",
                "change": "0.190",
                "changeRatio": "0.0487",
                "marketValue": "54049350",
                "volume": "24775",
                "turnoverRate": "0.0019",
                "regionName": "United States",
                "regionIsoCode": "US",
                "peTtm": "12.3082",
                "preClose": "3.900",
                "fiftyTwoWkHigh": "9.92",
                "fiftyTwoWkLow": "2.830",
                "open": "3.970",
                "high": "4.150",
                "low": "3.970",
                "vibrateRatio": "0.0564",
                "pprice": "3.48",
                "pchange": "0.000",
                "pchRatio": "0.0000"
            },
            "values": {
                "tickerId": 950173651,
                "change": "1.009",
                "changeRatio": "0.3275"
            }
        },
        {
            "ticker": {
                "tickerId": 950173576,
                "exchangeId": 95,
                "type": 2,
                "secType": [
                    61
                ],
                "regionId": 6,
                "currencyId": 247,
                "currencyCode": "USD",
                "name": "Marketwise Inc",
                "symbol": "MKTW",
                "disSymbol": "MKTW",
                "disExchangeCode": "NASDAQ",
                "exchangeCode": "NMS",
                "listStatus": 1,
                "template": "stock",
                "tradeTime": "2021-08-31T23:23:38.300+0000",
                "faTradeTime": "2021-08-31T23:23:38.300+0000",
                "status": "A",
                "close": "9.02",
                "change": "0.74",
                "changeRatio": "0.0894",
                "marketValue": "2878240471",
                "volume": "876060",
                "turnoverRate": "0.0027",
                "regionName": "United States",
                "regionIsoCode": "US",
                "peTtm": "-3.1481",
                "preClose": "8.28",
                "fiftyTwoWkHigh": "16.97",
                "fiftyTwoWkLow": "6.55",
                "open": "8.25",
                "high": "9.50",
                "low": "8.25",
                "vibrateRatio": "0.1498",
                "pprice": "9.28",
                "pchange": "0.26",
                "pchRatio": "0.0288"
            },
            "values": {
                "tickerId": 950173576,
                "change": "2.22",
                "changeRatio": "0.3265"
            }
        },
        {
            "ticker": {
                "tickerId": 950178203,
                "exchangeId": 11,
                "type": 2,
                "secType": [
                    61
                ],
                "regionId": 6,
                "currencyId": 247,
                "currencyCode": "USD",
                "name": "OppFi Inc",
                "symbol": "OPFI",
                "disSymbol": "OPFI",
                "disExchangeCode": "NYSE",
                "exchangeCode": "NYSE",
                "listStatus": 1,
                "template": "stock",
                "derivativeSupport": 1,
                "tradeTime": "2021-08-31T22:50:34.537+0000",
                "faTradeTime": "2021-08-31T22:50:34.537+0000",
                "status": "A",
                "close": "8.44",
                "change": "0.67",
                "changeRatio": "0.0862",
                "marketValue": "928102768",
                "volume": "455560",
                "turnoverRate": "0.0041",
                "regionName": "United States",
                "regionIsoCode": "US",
                "peTtm": "-8.9959",
                "preClose": "7.77",
                "fiftyTwoWkHigh": "11.60",
                "fiftyTwoWkLow": "6.01",
                "open": "7.91",
                "high": "8.68",
                "low": "7.80",
                "vibrateRatio": "0.1133",
                "pprice": "8.44",
                "pchange": "0.00",
                "pchRatio": "0.0000"
            },
            "values": {
                "tickerId": 950178203,
                "change": "2.05",
                "changeRatio": "0.3208"
            }
        },
        {
            "ticker": {
                "tickerId": 913253604,
                "exchangeId": 10,
                "type": 2,
                "secType": [
                    61
                ],
                "regionId": 6,
                "currencyId": 247,
                "currencyCode": "USD",
                "name": "Edesa Biotech Inc",
                "symbol": "EDSA",
                "disSymbol": "EDSA",
                "disExchangeCode": "NASDAQ",
                "exchangeCode": "NAS",
                "listStatus": 1,
                "template": "stock",
                "tradeTime": "2021-08-31T21:53:13.866+0000",
                "faTradeTime": "2021-08-31T21:53:13.866+0000",
                "status": "A",
                "close": "5.87",
                "change": "0.67",
                "changeRatio": "0.1288",
                "marketValue": "77810131",
                "volume": "189572",
                "turnoverRate": "0.0143",
                "regionName": "United States",
                "regionIsoCode": "US",
                "peTtm": "-5.7229",
                "preClose": "5.20",
                "fiftyTwoWkHigh": "10.15",
                "fiftyTwoWkLow": "4.055",
                "open": "5.25",
                "high": "5.87",
                "low": "5.20",
                "vibrateRatio": "0.1269",
                "pprice": "5.85",
                "pchange": "-0.02",
                "pchRatio": "-0.0034"
            },
            "values": {
                "tickerId": 913253604,
                "change": "1.41",
                "changeRatio": "0.3161"
            }
        },
        {
            "ticker": {
                "tickerId": 950145440,
                "exchangeId": 96,
                "type": 2,
                "secType": [
                    61
                ],
                "regionId": 6,
                "currencyId": 247,
                "currencyCode": "USD",
                "name": "AST SpaceMobile Inc",
                "symbol": "ASTS",
                "disSymbol": "ASTS",
                "disExchangeCode": "NASDAQ",
                "exchangeCode": "NSQ",
                "listStatus": 1,
                "template": "stock",
                "derivativeSupport": 1,
                "tradeTime": "2021-08-31T23:38:12.297+0000",
                "faTradeTime": "2021-08-31T23:38:12.297+0000",
                "status": "A",
                "close": "12.35",
                "change": "-0.01",
                "changeRatio": "-0.0008",
                "marketValue": "2241891844",
                "volume": "2081580",
                "turnoverRate": "0.0115",
                "regionName": "United States",
                "regionIsoCode": "US",
                "peTtm": "-10.4776",
                "preClose": "12.36",
                "fiftyTwoWkHigh": "25.37",
                "fiftyTwoWkLow": "6.96",
                "open": "12.28",
                "high": "12.66",
                "low": "11.58",
                "vibrateRatio": "0.0850",
                "pprice": "12.35",
                "pchange": "0.00",
                "pchRatio": "0.0000"
            },
            "values": {
                "tickerId": 950145440,
                "change": "2.91",
                "changeRatio": "0.3083"
            }
        },
        {
            "ticker": {
                "tickerId": 950183258,
                "exchangeId": 10,
                "type": 2,
                "secType": [
                    61
                ],
                "regionId": 6,
                "currencyId": 247,
                "currencyCode": "USD",
                "name": "Glimpse Group Inc (The)",
                "symbol": "VRAR",
                "disSymbol": "VRAR",
                "disExchangeCode": "NASDAQ",
                "exchangeCode": "NAS",
                "listStatus": 1,
                "template": "stock",
                "tradeTime": "2021-08-31T23:33:47.538+0000",
                "faTradeTime": "2021-08-31T23:33:47.538+0000",
                "status": "A",
                "close": "10.39",
                "change": "0.14",
                "changeRatio": "0.0137",
                "marketValue": "99244261",
                "volume": "637649",
                "turnoverRate": "0.0668",
                "regionName": "United States",
                "regionIsoCode": "US",
                "peTtm": "-15.7305",
                "preClose": "10.25",
                "fiftyTwoWkHigh": "18.45",
                "fiftyTwoWkLow": "7.44",
                "open": "10.53",
                "high": "11.47",
                "low": "9.82",
                "vibrateRatio": "0.1609",
                "pprice": "10.35",
                "pchange": "-0.04",
                "pchRatio": "-0.0039"
            },
            "values": {
                "tickerId": 950183258,
                "change": "2.42",
                "changeRatio": "0.3036"
            }
        },
        {
            "ticker": {
                "tickerId": 913253467,
                "exchangeId": 10,
                "type": 2,
                "secType": [
                    61
                ],
                "regionId": 6,
                "currencyId": 247,
                "currencyCode": "USD",
                "name": "Meta Materials Inc",
                "symbol": "MMAT",
                "disSymbol": "MMAT",
                "disExchangeCode": "NASDAQ",
                "exchangeCode": "NAS",
                "listStatus": 1,
                "template": "stock",
                "derivativeSupport": 1,
                "tradeTime": "2021-08-31T23:35:43.810+0000",
                "faTradeTime": "2021-08-31T23:35:43.810+0000",
                "status": "A",
                "close": "4.650",
                "change": "0.230",
                "changeRatio": "0.0520",
                "marketValue": "1300990271",
                "volume": "25337910",
                "turnoverRate": "0.0906",
                "regionName": "United States",
                "regionIsoCode": "US",
                "peTtm": "-12.4099",
                "preClose": "4.420",
                "fiftyTwoWkHigh": "21.76",
                "fiftyTwoWkLow": "0.4222",
                "open": "4.360",
                "high": "4.700",
                "low": "4.030",
                "vibrateRatio": "0.1512",
                "pprice": "4.60",
                "pchange": "-0.050",
                "pchRatio": "-0.0108"
            },
            "values": {
                "tickerId": 913253467,
                "change": "1.080",
                "changeRatio": "0.3025"
            }
        },
        {
            "ticker": {
                "tickerId": 950176676,
                "exchangeId": 10,
                "type": 2,
                "secType": [
                    61
                ],
                "regionId": 6,
                "currencyId": 247,
                "currencyCode": "USD",
                "name": "Virpax Pharmaceuticals, Inc.",
                "symbol": "VRPX",
                "disSymbol": "VRPX",
                "disExchangeCode": "NASDAQ",
                "exchangeCode": "NAS",
                "listStatus": 1,
                "template": "stock",
                "tradeTime": "2021-08-31T23:04:30.343+0000",
                "faTradeTime": "2021-08-31T23:04:30.343+0000",
                "status": "A",
                "close": "19.10",
                "change": "-0.82",
                "changeRatio": "-0.0412",
                "marketValue": "86117889",
                "volume": "568441",
                "turnoverRate": "0.1261",
                "regionName": "United States",
                "regionIsoCode": "US",
                "peTtm": "-12.2146",
                "preClose": "19.92",
                "fiftyTwoWkHigh": "36.00",
                "fiftyTwoWkLow": "3.700",
                "open": "20.00",
                "high": "21.20",
                "low": "18.34",
                "vibrateRatio": "0.1406",
                "pprice": "19.13",
                "pchange": "0.03",
                "pchRatio": "0.0016"
            },
            "values": {
                "tickerId": 950176676,
                "change": "4.43",
                "changeRatio": "0.3020"
            }
        },
        {
            "ticker": {
                "tickerId": 950052393,
                "exchangeId": 10,
                "type": 2,
                "secType": [
                    61
                ],
                "regionId": 6,
                "currencyId": 247,
                "currencyCode": "USD",
                "name": "Rekor Systems Inc",
                "symbol": "REKR",
                "disSymbol": "REKR",
                "disExchangeCode": "NASDAQ",
                "exchangeCode": "NAS",
                "listStatus": 1,
                "template": "stock",
                "derivativeSupport": 1,
                "tradeTime": "2021-08-31T23:06:44.526+0000",
                "faTradeTime": "2021-08-31T23:06:44.526+0000",
                "status": "A",
                "close": "10.92",
                "change": "0.97",
                "changeRatio": "0.0975",
                "marketValue": "448214577",
                "volume": "1883274",
                "turnoverRate": "0.0459",
                "regionName": "United States",
                "regionIsoCode": "US",
                "peTtm": "-16.7459",
                "preClose": "9.95",
                "fiftyTwoWkHigh": "25.38",
                "fiftyTwoWkLow": "3.090",
                "open": "10.03",
                "high": "11.60",
                "low": "9.97",
                "vibrateRatio": "0.1628",
                "pprice": "10.95",
                "pchange": "0.03",
                "pchRatio": "0.0027"
            },
            "values": {
                "tickerId": 950052393,
                "change": "2.53",
                "changeRatio": "0.3015"
            }
        },
        {
            "ticker": {
                "tickerId": 913253570,
                "exchangeId": 10,
                "type": 2,
                "secType": [
                    61
                ],
                "regionId": 6,
                "currencyId": 247,
                "currencyCode": "USD",
                "name": "Pieris Pharms",
                "symbol": "PIRS",
                "disSymbol": "PIRS",
                "disExchangeCode": "NASDAQ",
                "exchangeCode": "NAS",
                "listStatus": 1,
                "template": "stock",
                "derivativeSupport": 1,
                "tradeTime": "2021-08-31T23:28:03.908+0000",
                "faTradeTime": "2021-08-31T23:28:03.908+0000",
                "status": "A",
                "close": "5.39",
                "change": "0.40",
                "changeRatio": "0.0802",
                "marketValue": "359570737",
                "volume": "2986535",
                "turnoverRate": "0.0448",
                "regionName": "United States",
                "regionIsoCode": "US",
                "peTtm": "-6.3825",
                "preClose": "4.990",
                "fiftyTwoWkHigh": "5.36",
                "fiftyTwoWkLow": "1.700",
                "open": "5.00",
                "high": "5.44",
                "low": "4.960",
                "vibrateRatio": "0.0962",
                "pprice": "5.42",
                "pchange": "0.03",
                "pchRatio": "0.0056"
            },
            "values": {
                "tickerId": 913253570,
                "change": "1.24",
                "changeRatio": "0.2988"
            }
        },
        {
            "ticker": {
                "tickerId": 950099185,
                "exchangeId": 12,
                "type": 2,
                "secType": [
                    61
                ],
                "regionId": 6,
                "currencyId": 247,
                "currencyCode": "USD",
                "name": "Cybin Inc.",
                "symbol": "CYBN",
                "disSymbol": "CYBN",
                "disExchangeCode": "AMEX",
                "exchangeCode": "ASE",
                "listStatus": 1,
                "template": "stock",
                "tradeTime": "2021-08-31T23:03:47.915+0000",
                "faTradeTime": "2021-08-31T23:03:47.915+0000",
                "status": "A",
                "close": "2.800",
                "change": "0.070",
                "changeRatio": "0.0256",
                "marketValue": "446088526",
                "volume": "1415839",
                "turnoverRate": "0.0088",
                "regionName": "United States",
                "regionIsoCode": "US",
                "peTtm": "-10.6707",
                "preClose": "2.730",
                "fiftyTwoWkHigh": "3.380",
                "fiftyTwoWkLow": "0.4938",
                "open": "2.850",
                "high": "2.880",
                "low": "2.580",
                "vibrateRatio": "0.1099",
                "pprice": "2.84",
                "pchange": "0.040",
                "pchRatio": "0.0143"
            },
            "values": {
                "tickerId": 950099185,
                "change": "0.640",
                "changeRatio": "0.2963"
            }
        },
        {
            "ticker": {
                "tickerId": 925304190,
                "exchangeId": 10,
                "type": 2,
                "secType": [
                    61
                ],
                "regionId": 6,
                "currencyId": 247,
                "currencyCode": "USD",
                "name": "Ipsidy",
                "symbol": "AUID",
                "disSymbol": "AUID",
                "disExchangeCode": "NASDAQ",
                "exchangeCode": "NAS",
                "listStatus": 1,
                "template": "stock",
                "tradeTime": "2021-08-31T20:00:00.000+0000",
                "faTradeTime": "2021-08-31T13:30:01.510+0000",
                "status": "D",
                "close": "9.59",
                "change": "0.29",
                "changeRatio": "0.0312",
                "marketValue": "222041106",
                "volume": "111663",
                "turnoverRate": "0.0048",
                "regionName": "United States",
                "regionIsoCode": "US",
                "peTtm": "-19.5634",
                "preClose": "9.30",
                "fiftyTwoWkHigh": "14.00",
                "fiftyTwoWkLow": "2.400",
                "open": "9.13",
                "high": "9.92",
                "low": "9.13",
                "vibrateRatio": "0.0849",
                "pprice": "9.01",
                "pchange": "-0.29",
                "pchRatio": "-0.0312"
            },
            "values": {
                "tickerId": 925304190,
                "change": "2.19",
                "changeRatio": "0.2959"
            }
        },
        {
            "ticker": {
                "tickerId": 913255981,
                "exchangeId": 96,
                "type": 2,
                "secType": [
                    62
                ],
                "regionId": 6,
                "currencyId": 247,
                "currencyCode": "USD",
                "name": "Ascendis Pharma",
                "symbol": "ASND",
                "disSymbol": "ASND",
                "disExchangeCode": "NASDAQ",
                "exchangeCode": "NSQ",
                "listStatus": 1,
                "template": "stock",
                "derivativeSupport": 1,
                "tradeTime": "2021-08-31T20:55:37.461+0000",
                "faTradeTime": "2021-08-31T20:55:37.461+0000",
                "status": "A",
                "close": "156.73",
                "change": "2.45",
                "changeRatio": "0.0159",
                "marketValue": "8436678570",
                "volume": "229609",
                "turnoverRate": "0.0042",
                "regionName": "United States",
                "regionIsoCode": "US",
                "peTtm": "-15.4371",
                "preClose": "154.28",
                "fiftyTwoWkHigh": "183.98",
                "fiftyTwoWkLow": "109.36",
                "open": "154.28",
                "high": "158.30",
                "low": "154.28",
                "vibrateRatio": "0.0261",
                "pprice": "151.11",
                "pchange": "-5.62",
                "pchRatio": "-0.0359"
            },
            "values": {
                "tickerId": 913255981,
                "change": "34.98",
                "changeRatio": "0.2873"
            }
        },
        {
            "ticker": {
                "tickerId": 925173120,
                "exchangeId": 12,
                "type": 2,
                "secType": [
                    61
                ],
                "regionId": 6,
                "currencyId": 247,
                "currencyCode": "USD",
                "name": "Camber Energy",
                "symbol": "CEI",
                "disSymbol": "CEI",
                "disExchangeCode": "AMEX",
                "exchangeCode": "ASE",
                "listStatus": 1,
                "template": "stock",
                "tradeTime": "2021-08-31T23:22:51.429+0000",
                "faTradeTime": "2021-08-31T23:22:51.429+0000",
                "status": "A",
                "close": "0.5020",
                "change": "-0.0430",
                "changeRatio": "-0.0789",
                "marketValue": "52306038",
                "volume": "26440113",
                "turnoverRate": "0.2519",
                "regionName": "United States",
                "regionIsoCode": "US",
                "peTtm": "-0.2414",
                "preClose": "0.5450",
                "fiftyTwoWkHigh": "3.100",
                "fiftyTwoWkLow": "0.3300",
                "open": "0.5485",
                "high": "0.5500",
                "low": "0.4800",
                "vibrateRatio": "0.1264",
                "pprice": "0.4975",
                "pchange": "-0.0045",
                "pchRatio": "-0.0090"
            },
            "values": {
                "tickerId": 925173120,
                "change": "0.112",
                "changeRatio": "0.2862"
            }
        },
        {
            "ticker": {
                "tickerId": 913253749,
                "exchangeId": 10,
                "type": 2,
                "secType": [
                    61
                ],
                "regionId": 6,
                "currencyId": 247,
                "currencyCode": "USD",
                "name": "Dynavax Techs",
                "symbol": "DVAX",
                "disSymbol": "DVAX",
                "disExchangeCode": "NASDAQ",
                "exchangeCode": "NAS",
                "listStatus": 1,
                "template": "stock",
                "derivativeSupport": 1,
                "tradeTime": "2021-08-31T23:34:49.799+0000",
                "faTradeTime": "2021-08-31T23:34:49.799+0000",
                "status": "A",
                "close": "19.46",
                "change": "1.37",
                "changeRatio": "0.0757",
                "marketValue": "2233231390",
                "volume": "10138064",
                "turnoverRate": "0.0883",
                "regionName": "United States",
                "regionIsoCode": "US",
                "peTtm": "-350.6306",
                "preClose": "18.09",
                "fiftyTwoWkHigh": "18.60",
                "fiftyTwoWkLow": "3.580",
                "open": "18.26",
                "high": "20.00",
                "low": "18.26",
                "vibrateRatio": "0.0962",
                "pprice": "19.99",
                "pchange": "0.53",
                "pchRatio": "0.0272"
            },
            "values": {
                "tickerId": 913253749,
                "change": "4.33",
                "changeRatio": "0.2862"
            }
        }
    ]
}