{
    "rankType": "1m",
    "direction": -1,
    "hasMore": true,
    "latestUpdateTime": 1629506029378,
    "data": [
        {
            "ticker": {
                "tickerId": 950180950,
                "exchangeId": 10,
                "type": 2,
                "secType": [
                    61
                ],
                "regionId": 6,
                "currencyId": 247,
                "currencyCode": "USD",
                "name": "Flora Growth Corp.",
                "symbol": "FLGC",
                "disSymbol": "FLGC",
                "disExchangeCode": "NASDAQ",
                "exchangeCode": "NAS",
                "listStatus": 1,
                "template": "stock",
                "tradeTime": "2021-08-20T23:59:58.954+0000",
                "faTradeTime": "2021-08-20T23:59:58.954+0000",
                "status": "A",
                "close": "12.68",
                "change": "3.87",
                "changeRatio": "0.4393",
                "marketValue": "532861188",
                "volume": "38008961",
                "turnoverRate": "0.9045",
                "regionName": "United States",
                "regionIsoCode": "US",
                "peTtm": "-37.6038",
                "preClose": "8.81",
                "fiftyTwoWkHigh": "21.45",
                "fiftyTwoWkLow": "2.850",
                "open": "9.35",
                "high": "12.97",
                "low": "9.30",
                "vibrateRatio": "0.4154",
                "pprice": "12.65",
                "pchange": "-0.03",
                "pchRatio": "-0.0024"
            },
            "values": {
                "tickerId": 950180950,
                "change": "9.66",
                "changeRatio": "3.1987"
            }
        },
        {
            "ticker": {
                "tickerId": 950176676,
                "exchangeId": 10,
                "type": 2,
                "secType": [
                    61
                ],
                "regionId": 6,
                "currencyId": 247,
                "currencyCode": "USD",
                "name": "Virpax Pharmaceuticals, Inc.",
                "symbol": "VRPX",
                "disSymbol": "VRPX",
                "disExchangeCode": "NASDAQ",
                "exchangeCode": "NAS",
                "listStatus": 1,
                "template": "stock",
                "tradeTime": "2021-08-20T23:59:39.530+0000",
                "faTradeTime": "2021-08-20T23:59:39.530+0000",
                "status": "A",
                "close": "15.55",
                "change": "-1.67",
                "changeRatio": "-0.0970",
                "marketValue": "70111684",
                "volume": "5901221",
                "turnoverRate": "1.3088",
                "regionName": "United States",
                "regionIsoCode": "US",
                "peTtm": "-9.9444",
                "preClose": "17.22",
                "fiftyTwoWkHigh": "36.00",
                "fiftyTwoWkLow": "3.700",
                "open": "15.44",
                "high": "20.00",
                "low": "15.15",
                "vibrateRatio": "0.2811",
                "pprice": "15.61",
                "pchange": "0.06",
                "pchRatio": "0.0039"
            },
            "values": {
                "tickerId": 950176676,
                "change": "11.41",
                "changeRatio": "2.7560"
            }
        },
        {
            "ticker": {
                "tickerId": 950131471,
                "exchangeId": 95,
                "type": 2,
                "secType": [
                    61
                ],
                "regionId": 6,
                "currencyId": 247,
                "currencyCode": "USD",
                "name": "Fulcrum",
                "symbol": "FULC",
                "disSymbol": "FULC",
                "disExchangeCode": "NASDAQ",
                "exchangeCode": "NMS",
                "listStatus": 1,
                "template": "stock",
                "derivativeSupport": 1,
                "tradeTime": "2021-08-20T23:56:19.590+0000",
                "faTradeTime": "2021-08-20T23:56:19.590+0000",
                "status": "A",
                "close": "25.67",
                "change": "2.98",
                "changeRatio": "0.1313",
                "marketValue": "1009047269",
                "volume": "2120504",
                "turnoverRate": "0.0539",
                "regionName": "United States",
                "regionIsoCode": "US",
                "peTtm": "-10.3500",
                "preClose": "22.69",
                "fiftyTwoWkHigh": "26.89",
                "fiftyTwoWkLow": "6.85",
                "open": "22.55",
                "high": "25.98",
                "low": "22.34",
                "vibrateRatio": "0.1574",
                "pprice": "25.99",
                "pchange": "0.32",
                "pchRatio": "0.0125"
            },
            "values": {
                "tickerId": 950131471,
                "change": "17.67",
                "changeRatio": "2.2088"
            }
        },
        {
            "ticker": {
                "tickerId": 925418652,
                "exchangeId": 10,
                "type": 2,
                "secType": [
                    61
                ],
                "regionId": 6,
                "currencyId": 247,
                "currencyCode": "USD",
                "name": "Bit Digital Inc",
                "symbol": "BTBT",
                "disSymbol": "BTBT",
                "disExchangeCode": "NASDAQ",
                "exchangeCode": "NAS",
                "listStatus": 1,
                "template": "stock",
                "derivativeSupport": 1,
                "tradeTime": "2021-08-20T23:59:57.452+0000",
                "faTradeTime": "2021-08-20T23:59:57.452+0000",
                "status": "A",
                "close": "11.96",
                "change": "-0.12",
                "changeRatio": "-0.0099",
                "marketValue": "657689537",
                "volume": "29451471",
                "turnoverRate": "0.5356",
                "regionName": "United States",
                "regionIsoCode": "US",
                "peTtm": "384.5659",
                "preClose": "12.08",
                "fiftyTwoWkHigh": "33.00",
                "fiftyTwoWkLow": "3.400",
                "open": "12.53",
                "high": "13.58",
                "low": "11.62",
                "vibrateRatio": "0.1614",
                "pprice": "12.18",
                "pchange": "0.22",
                "pchRatio": "0.0184"
            },
            "values": {
                "tickerId": 925418652,
                "change": "7.73",
                "changeRatio": "1.8274"
            }
        },
        {
            "ticker": {
                "tickerId": 913303752,
                "exchangeId": 12,
                "type": 2,
                "secType": [
                    61
                ],
                "regionId": 6,
                "currencyId": 247,
                "currencyCode": "USD",
                "name": "AEROCENTURY",
                "symbol": "ACY",
                "disSymbol": "ACY",
                "disExchangeCode": "AMEX",
                "exchangeCode": "ASE",
                "listStatus": 1,
                "template": "stock",
                "tradeTime": "2021-08-20T20:09:51.243+0000",
                "faTradeTime": "2021-08-20T20:09:51.243+0000",
                "status": "A",
                "close": "30.94",
                "change": "0.51",
                "changeRatio": "0.0168",
                "marketValue": "47829650",
                "volume": "170159",
                "turnoverRate": "0.1101",
                "regionName": "United States",
                "regionIsoCode": "US",
                "peTtm": "-1.2763",
                "preClose": "30.43",
                "fiftyTwoWkHigh": "39.98",
                "fiftyTwoWkLow": "1.500",
                "open": "30.25",
                "high": "32.70",
                "low": "30.00",
                "vibrateRatio": "0.0883",
                "pprice": "30.5999",
                "pchange": "-0.34",
                "pchRatio": "-0.0110"
            },
            "values": {
                "tickerId": 913303752,
                "change": "18.79",
                "changeRatio": "1.5465"
            }
        },
        {
            "ticker": {
                "tickerId": 950175045,
                "exchangeId": 10,
                "type": 2,
                "secType": [
                    61
                ],
                "regionId": 6,
                "currencyId": 247,
                "currencyCode": "USD",
                "name": "MAXCYTE",
                "symbol": "MXCT",
                "disSymbol": "MXCT",
                "disExchangeCode": "NASDAQ",
                "exchangeCode": "NAS",
                "listStatus": 1,
                "template": "stock",
                "tradeTime": "2021-08-20T20:00:00.000+0000",
                "faTradeTime": "2021-08-20T13:29:31.161+0000",
                "status": "D",
                "close": "14.34",
                "change": "0.50",
                "changeRatio": "0.0361",
                "marketValue": "1437725575",
                "volume": "272171",
                "turnoverRate": "0.0027",
                "regionName": "United States",
                "regionIsoCode": "US",
                "peTtm": "-57.1998",
                "preClose": "13.84",
                "fiftyTwoWkHigh": "17.44",
                "fiftyTwoWkLow": "5.85",
                "open": "13.88",
                "high": "14.50",
                "low": "13.80",
                "vibrateRatio": "0.0506",
                "pprice": "13.89",
                "pchange": "0.05",
                "pchRatio": "0.0036"
            },
            "values": {
                "tickerId": 950175045,
                "change": "8.49",
                "changeRatio": "1.4513"
            }
        },
        {
            "ticker": {
                "tickerId": 925305494,
                "exchangeId": 96,
                "type": 2,
                "secType": [
                    61
                ],
                "regionId": 6,
                "currencyId": 247,
                "currencyCode": "USD",
                "name": "Score Media and Gaming",
                "symbol": "SCR",
                "disSymbol": "SCR",
                "disExchangeCode": "NASDAQ",
                "exchangeCode": "NSQ",
                "listStatus": 1,
                "template": "stock",
                "derivativeSupport": 1,
                "tradeTime": "2021-08-20T21:54:04.730+0000",
                "faTradeTime": "2021-08-20T21:54:04.730+0000",
                "status": "A",
                "close": "32.27",
                "change": "0.72",
                "changeRatio": "0.0228",
                "marketValue": "1705427194",
                "volume": "412745",
                "turnoverRate": "0.0078",
                "regionName": "United States",
                "regionIsoCode": "US",
                "peTtm": "-19.9518",
                "preClose": "31.55",
                "fiftyTwoWkHigh": "45.00",
                "fiftyTwoWkLow": "4.030",
                "open": "31.60",
                "high": "32.29",
                "low": "31.60",
                "vibrateRatio": "0.0219",
                "pprice": "32.27",
                "pchange": "0.00",
                "pchRatio": "0.0000"
            },
            "values": {
                "tickerId": 925305494,
                "change": "17.29",
                "changeRatio": "1.1542"
            }
        },
        {
            "ticker": {
                "tickerId": 950182577,
                "exchangeId": 10,
                "type": 2,
                "secType": [
                    61
                ],
                "regionId": 6,
                "currencyId": 247,
                "currencyCode": "USD",
                "name": "Regencell Bioscience Holdings Ltd",
                "symbol": "RGC",
                "disSymbol": "RGC",
                "disExchangeCode": "NASDAQ",
                "exchangeCode": "NAS",
                "listStatus": 1,
                "template": "stock",
                "tradeTime": "2021-08-20T23:59:56.766+0000",
                "faTradeTime": "2021-08-20T23:59:56.766+0000",
                "status": "A",
                "close": "19.16",
                "change": "12.86",
                "changeRatio": "2.0413",
                "marketValue": "242222731",
                "volume": "10298619",
                "turnoverRate": "0.8146",
                "regionName": "United States",
                "regionIsoCode": "US",
                "peTtm": "-285.5440",
                "preClose": "6.30",
                "fiftyTwoWkHigh": "13.20",
                "fiftyTwoWkLow": "6.24",
                "open": "6.00",
                "high": "26.70",
                "low": "6.00",
                "vibrateRatio": "3.175",
                "pprice": "15.43",
                "pchange": "-3.73",
                "pchRatio": "-0.1947"
            },
            "values": {
                "tickerId": 950182577,
                "change": "10.01",
                "changeRatio": "1.0940"
            }
        },
        {
            "ticker": {
                "tickerId": 925194354,
                "exchangeId": 10,
                "type": 2,
                "secType": [
                    61
                ],
                "regionId": 6,
                "currencyId": 247,
                "currencyCode": "USD",
                "name": "BeyondSpring",
                "symbol": "BYSI",
                "disSymbol": "BYSI",
                "disExchangeCode": "NASDAQ",
                "exchangeCode": "NAS",
                "listStatus": 1,
                "template": "stock",
                "derivativeSupport": 1,
                "tradeTime": "2021-08-20T23:58:08.890+0000",
                "faTradeTime": "2021-08-20T23:58:08.890+0000",
                "status": "A",
                "close": "20.19",
                "change": "0.46",
                "changeRatio": "0.0233",
                "marketValue": "789559750",
                "volume": "889770",
                "turnoverRate": "0.0228",
                "regionName": "United States",
                "regionIsoCode": "US",
                "peTtm": "-10.6814",
                "preClose": "19.73",
                "fiftyTwoWkHigh": "30.01",
                "fiftyTwoWkLow": "8.90",
                "open": "19.67",
                "high": "21.44",
                "low": "19.64",
                "vibrateRatio": "0.0895",
                "pprice": "20.47",
                "pchange": "0.28",
                "pchRatio": "0.0139"
            },
            "values": {
                "tickerId": 925194354,
                "change": "10.44",
                "changeRatio": "1.0708"
            }
        },
        {
            "ticker": {
                "tickerId": 925401987,
                "exchangeId": 10,
                "type": 2,
                "secType": [
                    61
                ],
                "regionId": 6,
                "currencyId": 247,
                "currencyCode": "USD",
                "name": "Kaixin Auto Holdings",
                "symbol": "KXIN",
                "disSymbol": "KXIN",
                "disExchangeCode": "NASDAQ",
                "exchangeCode": "NAS",
                "listStatus": 1,
                "template": "stock",
                "derivativeSupport": 0,
                "tradeTime": "2021-08-20T23:59:55.883+0000",
                "faTradeTime": "2021-08-20T23:59:55.883+0000",
                "status": "A",
                "close": "3.510",
                "change": "0.370",
                "changeRatio": "0.1178",
                "marketValue": "503546337",
                "volume": "10272437",
                "turnoverRate": "0.0716",
                "regionName": "United States",
                "regionIsoCode": "US",
                "peTtm": "-27.6161",
                "preClose": "3.140",
                "fiftyTwoWkHigh": "13.40",
                "fiftyTwoWkLow": "0.4001",
                "open": "3.130",
                "high": "3.690",
                "low": "3.100",
                "vibrateRatio": "0.1879",
                "pprice": "3.51",
                "pchange": "0.000",
                "pchRatio": "0.0000"
            },
            "values": {
                "tickerId": 925401987,
                "change": "1.600",
                "changeRatio": "0.8377"
            }
        },
        {
            "ticker": {
                "tickerId": 913254715,
                "exchangeId": 11,
                "type": 2,
                "secType": [
                    61
                ],
                "regionId": 6,
                "currencyId": 247,
                "currencyCode": "USD",
                "name": "LendingClub",
                "symbol": "LC",
                "disSymbol": "LC",
                "disExchangeCode": "NYSE",
                "exchangeCode": "NYSE",
                "listStatus": 1,
                "template": "stock",
                "derivativeSupport": 1,
                "tradeTime": "2021-08-20T23:58:28.997+0000",
                "faTradeTime": "2021-08-20T23:58:28.997+0000",
                "status": "A",
                "close": "28.70",
                "change": "2.18",
                "changeRatio": "0.0822",
                "marketValue": "2829854153",
                "volume": "2638111",
                "turnoverRate": "0.0268",
                "regionName": "United States",
                "regionIsoCode": "US",
                "peTtm": "-23.7131",
                "preClose": "26.52",
                "fiftyTwoWkHigh": "29.72",
                "fiftyTwoWkLow": "4.320",
                "open": "27.66",
                "high": "29.16",
                "low": "27.50",
                "vibrateRatio": "0.0626",
                "pprice": "28.89",
                "pchange": "0.19",
                "pchRatio": "0.0066"
            },
            "values": {
                "tickerId": 913254715,
                "change": "12.82",
                "changeRatio": "0.8073"
            }
        },
        {
            "ticker": {
                "tickerId": 950174696,
                "exchangeId": 95,
                "type": 2,
                "secType": [
                    61
                ],
                "regionId": 6,
                "currencyId": 247,
                "currencyCode": "USD",
                "name": "BITFARMS",
                "symbol": "BITF",
                "disSymbol": "BITF",
                "disExchangeCode": "NASDAQ",
                "exchangeCode": "NMS",
                "listStatus": 1,
                "template": "stock",
                "derivativeSupport": 1,
                "tradeTime": "2021-08-20T23:59:58.051+0000",
                "faTradeTime": "2021-08-20T23:59:58.051+0000",
                "status": "A",
                "close": "5.90",
                "change": "0.11",
                "changeRatio": "0.0190",
                "marketValue": "991129064",
                "volume": "8083837",
                "turnoverRate": "0.0481",
                "regionName": "United States",
                "regionIsoCode": "US",
                "peTtm": "-28.7805",
                "preClose": "5.79",
                "fiftyTwoWkHigh": "10.00",
                "fiftyTwoWkLow": "0.2135",
                "open": "5.96",
                "high": "6.28",
                "low": "5.81",
                "vibrateRatio": "0.0812",
                "pprice": "6.10",
                "pchange": "0.20",
                "pchRatio": "0.0339"
            },
            "values": {
                "tickerId": 950174696,
                "change": "2.61",
                "changeRatio": "0.7933"
            }
        },
        {
            "ticker": {
                "tickerId": 950184639,
                "exchangeId": 96,
                "type": 2,
                "secType": [
                    61
                ],
                "regionId": 6,
                "currencyId": 247,
                "currencyCode": "USD",
                "name": "monday.com Ltd.",
                "symbol": "MNDY",
                "disSymbol": "MNDY",
                "disExchangeCode": "NASDAQ",
                "exchangeCode": "NSQ",
                "listStatus": 1,
                "template": "stock",
                "derivativeSupport": 1,
                "tradeTime": "2021-08-20T23:40:38.645+0000",
                "faTradeTime": "2021-08-20T23:40:38.645+0000",
                "status": "A",
                "close": "352.28",
                "change": "3.20",
                "changeRatio": "0.0092",
                "marketValue": "15544474775",
                "volume": "259701",
                "turnoverRate": "0.0059",
                "regionName": "United States",
                "regionIsoCode": "US",
                "peTtm": "-89.7826",
                "preClose": "349.08",
                "fiftyTwoWkHigh": "358.00",
                "fiftyTwoWkLow": "155.01",
                "open": "350.00",
                "high": "364.13",
                "low": "344.34",
                "vibrateRatio": "0.0567",
                "pprice": "351.00",
                "pchange": "-1.28",
                "pchRatio": "-0.0036"
            },
            "values": {
                "tickerId": 950184639,
                "change": "147.35",
                "changeRatio": "0.7190"
            }
        },
        {
            "ticker": {
                "tickerId": 913253663,
                "exchangeId": 10,
                "type": 2,
                "secType": [
                    61
                ],
                "regionId": 6,
                "currencyId": 247,
                "currencyCode": "USD",
                "name": "Allied Hlthcare",
                "symbol": "AHPI",
                "disSymbol": "AHPI",
                "disExchangeCode": "NASDAQ",
                "exchangeCode": "NAS",
                "listStatus": 1,
                "template": "stock",
                "tradeTime": "2021-08-20T23:53:26.127+0000",
                "faTradeTime": "2021-08-20T23:53:26.127+0000",
                "status": "A",
                "close": "9.31",
                "change": "0.31",
                "changeRatio": "0.0344",
                "marketValue": "37366029",
                "volume": "874853",
                "turnoverRate": "0.2180",
                "regionName": "United States",
                "regionIsoCode": "US",
                "peTtm": "-91.9052",
                "preClose": "9.00",
                "fiftyTwoWkHigh": "16.41",
                "fiftyTwoWkLow": "3.451",
                "open": "8.98",
                "high": "9.58",
                "low": "8.95",
                "vibrateRatio": "0.0633",
                "pprice": "9.26",
                "pchange": "-0.05",
                "pchRatio": "-0.0054"
            },
            "values": {
                "tickerId": 913253663,
                "change": "3.83",
                "changeRatio": "0.6989"
            }
        },
        {
            "ticker": {
                "tickerId": 950177837,
                "exchangeId": 96,
                "type": 2,
                "secType": [
                    61
                ],
                "regionId": 6,
                "currencyId": 247,
                "currencyCode": "USD",
                "name": "Upstart Holdings, Inc.",
                "symbol": "UPST",
                "disSymbol": "UPST",
                "disExchangeCode": "NASDAQ",
                "exchangeCode": "NSQ",
                "listStatus": 1,
                "template": "stock",
                "derivativeSupport": 1,
                "tradeTime": "2021-08-20T23:48:47.749+0000",
                "faTradeTime": "2021-08-20T23:48:47.749+0000",
                "status": "A",
                "close": "195.64",
                "change": "1.77",
                "changeRatio": "0.0091",
                "marketValue": "14176246758",
                "volume": "6125590",
                "turnoverRate": "0.0845",
                "regionName": "United States",
                "regionIsoCode": "US",
                "peTtm": "300.4761",
                "preClose": "193.87",
                "fiftyTwoWkHigh": "220.11",
                "fiftyTwoWkLow": "22.61",
                "open": "197.15",
                "high": "208.60",
                "low": "192.51",
                "vibrateRatio": "0.0830",
                "pprice": "196.00",
                "pchange": "0.36",
                "pchRatio": "0.0018"
            },
            "values": {
                "tickerId": 950177837,
                "change": "79.07",
                "changeRatio": "0.6783"
            }
        },
        {
            "ticker": {
                "tickerId": 950129176,
                "exchangeId": 95,
                "type": 2,
                "secType": [
                    61
                ],
                "regionId": 6,
                "currencyId": 247,
                "currencyCode": "USD",
                "name": "Golden Nugget Online Gaming Inc",
                "symbol": "GNOG",
                "disSymbol": "GNOG",
                "disExchangeCode": "NASDAQ",
                "exchangeCode": "NMS",
                "listStatus": 1,
                "template": "stock",
                "derivativeSupport": 1,
                "tradeTime": "2021-08-20T23:48:35.118+0000",
                "faTradeTime": "2021-08-20T23:48:35.118+0000",
                "status": "A",
                "close": "18.86",
                "change": "0.29",
                "changeRatio": "0.0156",
                "marketValue": "1475378967",
                "volume": "881653",
                "turnoverRate": "0.0113",
                "regionName": "United States",
                "regionIsoCode": "US",
                "peTtm": "16.4947",
                "preClose": "18.57",
                "fiftyTwoWkHigh": "27.18",
                "fiftyTwoWkLow": "10.10",
                "open": "18.55",
                "high": "18.91",
                "low": "18.49",
                "vibrateRatio": "0.0226",
                "pprice": "18.85",
                "pchange": "-0.01",
                "pchRatio": "-0.0005"
            },
            "values": {
                "tickerId": 950129176,
                "change": "7.60",
                "changeRatio": "0.6750"
            }
        },
        {
            "ticker": {
                "tickerId": 913254570,
                "exchangeId": 11,
                "type": 2,
                "secType": [
                    62
                ],
                "regionId": 6,
                "currencyId": 247,
                "currencyCode": "USD",
                "name": "BIT Mining Ltd",
                "symbol": "BTCM",
                "disSymbol": "BTCM",
                "disExchangeCode": "NYSE",
                "exchangeCode": "NYSE",
                "listStatus": 1,
                "template": "stock",
                "derivativeSupport": 1,
                "tradeTime": "2021-08-20T23:59:48.670+0000",
                "faTradeTime": "2021-08-20T23:59:48.670+0000",
                "status": "A",
                "close": "7.47",
                "change": "0.80",
                "changeRatio": "0.1199",
                "marketValue": "458904763",
                "volume": "2750830",
                "turnoverRate": "0.0448",
                "regionName": "United States",
                "regionIsoCode": "US",
                "peTtm": "-12.0484",
                "preClose": "6.67",
                "fiftyTwoWkHigh": "35.00",
                "fiftyTwoWkLow": "2.510",
                "open": "6.87",
                "high": "7.68",
                "low": "6.79",
                "vibrateRatio": "0.1319",
                "pprice": "7.70",
                "pchange": "0.23",
                "pchRatio": "0.0308"
            },
            "values": {
                "tickerId": 913254570,
                "change": "2.93",
                "changeRatio": "0.6454"
            }
        },
        {
            "ticker": {
                "tickerId": 950186899,
                "exchangeId": 11,
                "type": 2,
                "secType": [
                    61
                ],
                "regionId": 6,
                "currencyId": 247,
                "currencyCode": "USD",
                "name": "VICTORIAAS SECRT",
                "symbol": "VSCO",
                "disSymbol": "VSCO",
                "disExchangeCode": "NYSE",
                "exchangeCode": "NYSE",
                "listStatus": 1,
                "template": "stock",
                "derivativeSupport": 1,
                "tradeTime": "2021-08-20T23:19:53.116+0000",
                "faTradeTime": "2021-08-20T23:19:53.116+0000",
                "status": "A",
                "close": "69.11",
                "change": "-0.04",
                "changeRatio": "-0.0006",
                "marketValue": "6098925225",
                "volume": "1939591",
                "turnoverRate": "0.0220",
                "regionName": "United States",
                "regionIsoCode": "US",
                "peTtm": "15.9434",
                "preClose": "69.15",
                "fiftyTwoWkHigh": "76.00",
                "fiftyTwoWkLow": "39.79",
                "open": "69.35",
                "high": "70.69",
                "low": "68.00",
                "vibrateRatio": "0.0389",
                "pprice": "68.50",
                "pchange": "-0.61",
                "pchRatio": "-0.0088"
            },
            "values": {
                "tickerId": 950186899,
                "change": "26.97",
                "changeRatio": "0.6400"
            }
        },
        {
            "ticker": {
                "tickerId": 925418477,
                "exchangeId": 96,
                "type": 2,
                "secType": [
                    61
                ],
                "regionId": 6,
                "currencyId": 247,
                "currencyCode": "USD",
                "name": "Hut 8 Mining",
                "symbol": "HUT",
                "disSymbol": "HUT",
                "disExchangeCode": "NASDAQ",
                "exchangeCode": "NSQ",
                "listStatus": 1,
                "template": "stock",
                "derivativeSupport": 1,
                "tradeTime": "2021-08-20T23:59:34.447+0000",
                "faTradeTime": "2021-08-20T23:59:34.447+0000",
                "status": "A",
                "close": "6.61",
                "change": "0.43",
                "changeRatio": "0.0696",
                "marketValue": "948407671",
                "volume": "5801475",
                "turnoverRate": "0.0404",
                "regionName": "United States",
                "regionIsoCode": "US",
                "peTtm": "21.3708",
                "preClose": "6.18",
                "fiftyTwoWkHigh": "13.00",
                "fiftyTwoWkLow": "0.5850",
                "open": "6.34",
                "high": "6.85",
                "low": "6.31",
                "vibrateRatio": "0.0875",
                "pprice": "6.87",
                "pchange": "0.26",
                "pchRatio": "0.0393"
            },
            "values": {
                "tickerId": 925418477,
                "change": "2.52",
                "changeRatio": "0.6161"
            }
        },
        {
            "ticker": {
                "tickerId": 950144758,
                "exchangeId": 95,
                "type": 2,
                "secType": [
                    61
                ],
                "regionId": 6,
                "currencyId": 247,
                "currencyCode": "USD",
                "name": "SITIME CORP",
                "symbol": "SITM",
                "disSymbol": "SITM",
                "disExchangeCode": "NASDAQ",
                "exchangeCode": "NMS",
                "listStatus": 1,
                "template": "stock",
                "derivativeSupport": 1,
                "tradeTime": "2021-08-20T20:00:00.000+0000",
                "faTradeTime": "2021-08-20T20:01:21.737+0000",
                "status": "A",
                "close": "206.38",
                "change": "5.00",
                "changeRatio": "0.0248",
                "marketValue": "3933765221",
                "volume": "200542",
                "turnoverRate": "0.0105",
                "regionName": "United States",
                "regionIsoCode": "US",
                "peTtm": "-8093.3333",
                "preClose": "201.38",
                "fiftyTwoWkHigh": "208.49",
                "fiftyTwoWkLow": "63.00",
                "open": "200.80",
                "high": "207.44",
                "low": "197.29",
                "vibrateRatio": "0.0504",
                "pprice": "206.38",
                "pchange": "0.00",
                "pchRatio": "0.0000"
            },
            "values": {
                "tickerId": 950144758,
                "change": "78.36",
                "changeRatio": "0.6121"
            }
        },
        {
            "ticker": {
                "tickerId": 950183495,
                "exchangeId": 96,
                "type": 2,
                "secType": [
                    61
                ],
                "regionId": 6,
                "currencyId": 247,
                "currencyCode": "USD",
                "name": "TaskUs, Inc.",
                "symbol": "TASK",
                "disSymbol": "TASK",
                "disExchangeCode": "NASDAQ",
                "exchangeCode": "NSQ",
                "listStatus": 1,
                "template": "stock",
                "tradeTime": "2021-08-20T20:54:58.244+0000",
                "faTradeTime": "2021-08-20T20:54:58.244+0000",
                "status": "A",
                "close": "49.42",
                "change": "3.25",
                "changeRatio": "0.0704",
                "marketValue": "4808080399",
                "volume": "566296",
                "turnoverRate": "0.0058",
                "regionName": "United States",
                "regionIsoCode": "US",
                "peTtm": "139.2113",
                "preClose": "46.17",
                "fiftyTwoWkHigh": "49.50",
                "fiftyTwoWkLow": "26.66",
                "open": "46.17",
                "high": "50.98",
                "low": "45.77",
                "vibrateRatio": "0.1129",
                "pprice": "49.75",
                "pchange": "0.33",
                "pchRatio": "0.0067"
            },
            "values": {
                "tickerId": 950183495,
                "change": "18.68",
                "changeRatio": "0.6077"
            }
        },
        {
            "ticker": {
                "tickerId": 950179452,
                "exchangeId": 10,
                "type": 2,
                "secType": [
                    61
                ],
                "regionId": 6,
                "currencyId": 247,
                "currencyCode": "USD",
                "name": "Agrify Corp",
                "symbol": "AGFY",
                "disSymbol": "AGFY",
                "disExchangeCode": "NASDAQ",
                "exchangeCode": "NAS",
                "listStatus": 1,
                "template": "stock",
                "derivativeSupport": 1,
                "tradeTime": "2021-08-20T23:34:08.560+0000",
                "faTradeTime": "2021-08-20T23:34:08.560+0000",
                "status": "A",
                "close": "31.88",
                "change": "2.34",
                "changeRatio": "0.0792",
                "marketValue": "391543465",
                "volume": "639007",
                "turnoverRate": "0.0520",
                "regionName": "United States",
                "regionIsoCode": "US",
                "peTtm": "-21.7923",
                "preClose": "29.54",
                "fiftyTwoWkHigh": "33.17",
                "fiftyTwoWkLow": "6.81",
                "open": "29.14",
                "high": "31.99",
                "low": "28.82",
                "vibrateRatio": "0.1073",
                "pprice": "31.81",
                "pchange": "-0.07",
                "pchRatio": "-0.0022"
            },
            "values": {
                "tickerId": 950179452,
                "change": "12.05",
                "changeRatio": "0.6077"
            }
        },
        {
            "ticker": {
                "tickerId": 913257452,
                "exchangeId": 10,
                "type": 2,
                "secType": [
                    62
                ],
                "regionId": 6,
                "currencyId": 247,
                "currencyCode": "USD",
                "name": "The9 Ltd",
                "symbol": "NCTY",
                "disSymbol": "NCTY",
                "disExchangeCode": "NASDAQ",
                "exchangeCode": "NAS",
                "listStatus": 1,
                "template": "stock",
                "derivativeSupport": 1,
                "tradeTime": "2021-08-20T23:59:09.483+0000",
                "faTradeTime": "2021-08-20T23:59:09.483+0000",
                "status": "A",
                "close": "13.91",
                "change": "1.02",
                "changeRatio": "0.0791",
                "marketValue": "164121335",
                "volume": "5103536",
                "turnoverRate": "0.4325",
                "regionName": "United States",
                "regionIsoCode": "US",
                "peTtm": "0.8331",
                "preClose": "12.89",
                "fiftyTwoWkHigh": "89.20",
                "fiftyTwoWkLow": "2.040",
                "open": "13.61",
                "high": "14.58",
                "low": "13.46",
                "vibrateRatio": "0.0861",
                "pprice": "14.10",
                "pchange": "0.19",
                "pchRatio": "0.0137"
            },
            "values": {
                "tickerId": 913257452,
                "change": "5.23",
                "changeRatio": "0.6025"
            }
        },
        {
            "ticker": {
                "tickerId": 950186334,
                "exchangeId": 96,
                "type": 2,
                "secType": [
                    61
                ],
                "regionId": 6,
                "currencyId": 247,
                "currencyCode": "USD",
                "name": "Caribou Biosciences, Inc.",
                "symbol": "CRBU",
                "disSymbol": "CRBU",
                "disExchangeCode": "NASDAQ",
                "exchangeCode": "NSQ",
                "listStatus": 1,
                "template": "stock",
                "tradeTime": "2021-08-20T20:41:40.231+0000",
                "faTradeTime": "2021-08-20T20:41:40.231+0000",
                "status": "A",
                "close": "26.09",
                "change": "0.67",
                "changeRatio": "0.0264",
                "marketValue": "1553899293",
                "volume": "845824",
                "turnoverRate": "0.0142",
                "regionName": "United States",
                "regionIsoCode": "US",
                "peTtm": "-39.2803",
                "preClose": "25.42",
                "fiftyTwoWkHigh": "29.00",
                "fiftyTwoWkLow": "15.00",
                "open": "26.02",
                "high": "26.80",
                "low": "25.61",
                "vibrateRatio": "0.0460",
                "pprice": "26.09",
                "pchange": "0.00",
                "pchRatio": "0.0000"
            },
            "values": {
                "tickerId": 950186334,
                "change": "9.77",
                "changeRatio": "0.5987"
            }
        },
        {
            "ticker": {
                "tickerId": 913324149,
                "exchangeId": 95,
                "type": 2,
                "secType": [
                    61
                ],
                "regionId": 6,
                "currencyId": 247,
                "currencyCode": "USD",
                "name": "Pixelworks",
                "symbol": "PXLW",
                "disSymbol": "PXLW",
                "disExchangeCode": "NASDAQ",
                "exchangeCode": "NMS",
                "listStatus": 1,
                "template": "stock",
                "derivativeSupport": 1,
                "tradeTime": "2021-08-20T23:59:10.458+0000",
                "faTradeTime": "2021-08-20T23:59:10.458+0000",
                "status": "A",
                "close": "4.450",
                "change": "0.890",
                "changeRatio": "0.2500",
                "marketValue": "233332265",
                "volume": "11578698",
                "turnoverRate": "0.2208",
                "regionName": "United States",
                "regionIsoCode": "US",
                "peTtm": "-7.5822",
                "preClose": "3.560",
                "fiftyTwoWkHigh": "4.670",
                "fiftyTwoWkLow": "1.847",
                "open": "3.690",
                "high": "4.480",
                "low": "3.690",
                "vibrateRatio": "0.2219",
                "pprice": "4.51",
                "pchange": "0.060",
                "pchRatio": "0.0135"
            },
            "values": {
                "tickerId": 913324149,
                "change": "1.640",
                "changeRatio": "0.5836"
            }
        },
        {
            "ticker": {
                "tickerId": 913431441,
                "exchangeId": 10,
                "type": 2,
                "secType": [
                    61
                ],
                "regionId": 6,
                "currencyId": 247,
                "currencyCode": "USD",
                "name": "Shineco",
                "symbol": "TYHT",
                "disSymbol": "TYHT",
                "disExchangeCode": "NASDAQ",
                "exchangeCode": "NAS",
                "listStatus": 1,
                "template": "stock",
                "tradeTime": "2021-08-20T23:21:18.563+0000",
                "faTradeTime": "2021-08-20T23:21:18.563+0000",
                "status": "A",
                "close": "6.99",
                "change": "0.24",
                "changeRatio": "0.0356",
                "marketValue": "55091559",
                "volume": "157760",
                "turnoverRate": "0.0200",
                "regionName": "United States",
                "regionIsoCode": "US",
                "peTtm": "-0.9754",
                "preClose": "6.75",
                "fiftyTwoWkHigh": "19.40",
                "fiftyTwoWkLow": "2.100",
                "open": "6.70",
                "high": "7.08",
                "low": "6.65",
                "vibrateRatio": "0.0622",
                "pprice": "6.83",
                "pchange": "-0.16",
                "pchRatio": "-0.0229"
            },
            "values": {
                "tickerId": 913431441,
                "change": "2.53",
                "changeRatio": "0.5673"
            }
        },
        {
            "ticker": {
                "tickerId": 913254377,
                "exchangeId": 11,
                "type": 2,
                "secType": [
                    61
                ],
                "regionId": 6,
                "currencyId": 247,
                "currencyCode": "USD",
                "name": "Ryerson Holding",
                "symbol": "RYI",
                "disSymbol": "RYI",
                "disExchangeCode": "NYSE",
                "exchangeCode": "NYSE",
                "listStatus": 1,
                "template": "stock",
                "derivativeSupport": 1,
                "tradeTime": "2021-08-20T20:00:00.000+0000",
                "faTradeTime": "2021-08-20T20:01:13.992+0000",
                "status": "A",
                "close": "22.22",
                "change": "0.08",
                "changeRatio": "0.0036",
                "marketValue": "854905478",
                "volume": "104222",
                "turnoverRate": "0.0027",
                "regionName": "United States",
                "regionIsoCode": "US",
                "peTtm": "10.6194",
                "preClose": "22.14",
                "fiftyTwoWkHigh": "25.68",
                "fiftyTwoWkLow": "5.24",
                "open": "22.09",
                "high": "22.47",
                "low": "21.48",
                "vibrateRatio": "0.0456",
                "pprice": "22.22",
                "pchange": "0.00",
                "pchRatio": "0.0000"
            },
            "values": {
                "tickerId": 913254377,
                "change": "8.01",
                "changeRatio": "0.5637"
            }
        },
        {
            "ticker": {
                "tickerId": 913255732,
                "exchangeId": 95,
                "type": 2,
                "secType": [
                    61
                ],
                "regionId": 6,
                "currencyId": 247,
                "currencyCode": "USD",
                "name": "Arcturus",
                "symbol": "ARCT",
                "disSymbol": "ARCT",
                "disExchangeCode": "NASDAQ",
                "exchangeCode": "NMS",
                "listStatus": 1,
                "template": "stock",
                "derivativeSupport": 1,
                "tradeTime": "2021-08-20T21:57:12.488+0000",
                "faTradeTime": "2021-08-20T21:57:12.488+0000",
                "status": "A",
                "close": "47.90",
                "change": "1.97",
                "changeRatio": "0.0429",
                "marketValue": "1260741124",
                "volume": "423976",
                "turnoverRate": "0.0161",
                "regionName": "United States",
                "regionIsoCode": "US",
                "peTtm": "-7.5028",
                "preClose": "45.93",
                "fiftyTwoWkHigh": "129.71",
                "fiftyTwoWkLow": "24.87",
                "open": "45.44",
                "high": "47.95",
                "low": "45.10",
                "vibrateRatio": "0.0603",
                "pprice": "47.01",
                "pchange": "-0.89",
                "pchRatio": "-0.0186"
            },
            "values": {
                "tickerId": 913255732,
                "change": "16.68",
                "changeRatio": "0.5343"
            }
        },
        {
            "ticker": {
                "tickerId": 913917856,
                "exchangeId": 11,
                "type": 2,
                "secType": [
                    61
                ],
                "regionId": 6,
                "currencyId": 247,
                "currencyCode": "USD",
                "name": "SandRidge",
                "symbol": "SD",
                "disSymbol": "SD",
                "disExchangeCode": "NYSE",
                "exchangeCode": "NYSE",
                "listStatus": 1,
                "template": "stock",
                "derivativeSupport": 1,
                "tradeTime": "2021-08-20T21:18:46.988+0000",
                "faTradeTime": "2021-08-20T21:18:46.988+0000",
                "status": "A",
                "close": "8.54",
                "change": "0.64",
                "changeRatio": "0.0810",
                "marketValue": "312468138",
                "volume": "500481",
                "turnoverRate": "0.0137",
                "regionName": "United States",
                "regionIsoCode": "US",
                "peTtm": "1897.7778",
                "preClose": "7.90",
                "fiftyTwoWkHigh": "8.84",
                "fiftyTwoWkLow": "1.548",
                "open": "7.78",
                "high": "8.62",
                "low": "7.72",
                "vibrateRatio": "0.1133",
                "pprice": "8.60",
                "pchange": "0.06",
                "pchRatio": "0.0070"
            },
            "values": {
                "tickerId": 913917856,
                "change": "2.97",
                "changeRatio": "0.5332"
            }
        },
        {
            "ticker": {
                "tickerId": 913255815,
                "exchangeId": 95,
                "type": 2,
                "secType": [
                    61
                ],
                "regionId": 6,
                "currencyId": 247,
                "currencyCode": "USD",
                "name": "Travere Therapeutics",
                "symbol": "TVTX",
                "disSymbol": "TVTX",
                "disExchangeCode": "NASDAQ",
                "exchangeCode": "NMS",
                "listStatus": 1,
                "template": "stock",
                "derivativeSupport": 1,
                "tradeTime": "2021-08-20T23:51:44.530+0000",
                "faTradeTime": "2021-08-20T23:51:44.530+0000",
                "status": "A",
                "close": "20.19",
                "change": "0.28",
                "changeRatio": "0.0141",
                "marketValue": "1225879783",
                "volume": "1490744",
                "turnoverRate": "0.0246",
                "regionName": "United States",
                "regionIsoCode": "US",
                "peTtm": "-4.5636",
                "preClose": "19.91",
                "fiftyTwoWkHigh": "33.09",
                "fiftyTwoWkLow": "12.75",
                "open": "19.93",
                "high": "20.57",
                "low": "19.85",
                "vibrateRatio": "0.0362",
                "pprice": "19.95",
                "pchange": "-0.24",
                "pchRatio": "-0.0119"
            },
            "values": {
                "tickerId": 913255815,
                "change": "6.96",
                "changeRatio": "0.5261"
            }
        },
        {
            "ticker": {
                "tickerId": 950185315,
                "exchangeId": 96,
                "type": 2,
                "secType": [
                    61
                ],
                "regionId": 6,
                "currencyId": 247,
                "currencyCode": "USD",
                "name": "Monte Rosa Therapeutics, Inc.",
                "symbol": "GLUE",
                "disSymbol": "GLUE",
                "disExchangeCode": "NASDAQ",
                "exchangeCode": "NSQ",
                "listStatus": 1,
                "template": "stock",
                "tradeTime": "2021-08-20T20:00:00.000+0000",
                "status": "D",
                "close": "35.24",
                "change": "1.96",
                "changeRatio": "0.0589",
                "marketValue": "1634498825",
                "volume": "139543",
                "turnoverRate": "0.0030",
                "regionName": "United States",
                "regionIsoCode": "US",
                "peTtm": "-35.7512",
                "preClose": "33.28",
                "fiftyTwoWkHigh": "35.82",
                "fiftyTwoWkLow": "18.01",
                "open": "33.40",
                "high": "35.46",
                "low": "33.29",
                "vibrateRatio": "0.0619",
                "pprice": "33.28",
                "pchange": "0.00",
                "pchRatio": "0.0000"
            },
            "values": {
                "tickerId": 950185315,
                "change": "11.87",
                "changeRatio": "0.5079"
            }
        },
        {
            "ticker": {
                "tickerId": 913303892,
                "exchangeId": 95,
                "type": 2,
                "secType": [
                    61
                ],
                "regionId": 6,
                "currencyId": 247,
                "currencyCode": "USD",
                "name": "IEC ELECTRONICS",
                "symbol": "IEC",
                "disSymbol": "IEC",
                "disExchangeCode": "NASDAQ",
                "exchangeCode": "NMS",
                "listStatus": 1,
                "template": "stock",
                "derivativeSupport": 1,
                "tradeTime": "2021-08-20T21:20:11.535+0000",
                "faTradeTime": "2021-08-20T21:20:11.535+0000",
                "status": "A",
                "close": "15.20",
                "change": "-0.03",
                "changeRatio": "-0.0020",
                "marketValue": "161480772",
                "volume": "80731",
                "turnoverRate": "0.0076",
                "regionName": "United States",
                "regionIsoCode": "US",
                "peTtm": "40.3076",
                "preClose": "15.23",
                "fiftyTwoWkHigh": "17.98",
                "fiftyTwoWkLow": "8.30",
                "open": "15.22",
                "high": "15.22",
                "low": "15.20",
                "vibrateRatio": "0.0013",
                "pprice": "15.20",
                "pchange": "0.00",
                "pchRatio": "0.0000"
            },
            "values": {
                "tickerId": 913303892,
                "change": "5.04",
                "changeRatio": "0.4961"
            }
        },
        {
            "ticker": {
                "tickerId": 913255912,
                "exchangeId": 10,
                "type": 2,
                "secType": [
                    61
                ],
                "regionId": 6,
                "currencyId": 247,
                "currencyCode": "USD",
                "name": "Sphere 3D",
                "symbol": "ANY",
                "disSymbol": "ANY",
                "disExchangeCode": "NASDAQ",
                "exchangeCode": "NAS",
                "listStatus": 1,
                "template": "stock",
                "derivativeSupport": 1,
                "tradeTime": "2021-08-20T23:59:40.885+0000",
                "faTradeTime": "2021-08-20T23:59:40.885+0000",
                "status": "A",
                "close": "4.020",
                "change": "0.430",
                "changeRatio": "0.1198",
                "marketValue": "90779756",
                "volume": "8329028",
                "turnoverRate": "0.3688",
                "regionName": "United States",
                "regionIsoCode": "US",
                "peTtm": "-3.8451",
                "preClose": "3.590",
                "fiftyTwoWkHigh": "6.58",
                "fiftyTwoWkLow": "1.230",
                "open": "3.729",
                "high": "4.160",
                "low": "3.650",
                "vibrateRatio": "0.1406",
                "pprice": "4.11",
                "pchange": "0.090",
                "pchRatio": "0.0224"
            },
            "values": {
                "tickerId": 913255912,
                "change": "1.310",
                "changeRatio": "0.4834"
            }
        },
        {
            "ticker": {
                "tickerId": 913256090,
                "exchangeId": 96,
                "type": 2,
                "secType": [
                    61
                ],
                "regionId": 6,
                "currencyId": 247,
                "currencyCode": "USD",
                "name": "Editas Medicine",
                "symbol": "EDIT",
                "disSymbol": "EDIT",
                "disExchangeCode": "NASDAQ",
                "exchangeCode": "NSQ",
                "listStatus": 1,
                "template": "stock",
                "derivativeSupport": 1,
                "tradeTime": "2021-08-20T23:58:37.645+0000",
                "faTradeTime": "2021-08-20T23:58:37.645+0000",
                "status": "A",
                "close": "60.38",
                "change": "2.28",
                "changeRatio": "0.0392",
                "marketValue": "4121614576",
                "volume": "899458",
                "turnoverRate": "0.0132",
                "regionName": "United States",
                "regionIsoCode": "US",
                "peTtm": "-23.6589",
                "preClose": "58.10",
                "fiftyTwoWkHigh": "99.95",
                "fiftyTwoWkLow": "27.01",
                "open": "58.05",
                "high": "61.78",
                "low": "57.97",
                "vibrateRatio": "0.0647",
                "pprice": "62.89",
                "pchange": "2.51",
                "pchRatio": "0.0416"
            },
            "values": {
                "tickerId": 913256090,
                "change": "19.54",
                "changeRatio": "0.4785"
            }
        },
        {
            "ticker": {
                "tickerId": 913254273,
                "exchangeId": 11,
                "type": 2,
                "secType": [
                    61
                ],
                "regionId": 6,
                "currencyId": 247,
                "currencyCode": "USD",
                "name": "Express",
                "symbol": "EXPR",
                "disSymbol": "EXPR",
                "disExchangeCode": "NYSE",
                "exchangeCode": "NYSE",
                "listStatus": 1,
                "template": "stock",
                "derivativeSupport": 1,
                "tradeTime": "2021-08-20T23:59:25.939+0000",
                "faTradeTime": "2021-08-20T23:59:25.939+0000",
                "status": "A",
                "close": "6.72",
                "change": "0.33",
                "changeRatio": "0.0516",
                "marketValue": "445534481",
                "volume": "7731753",
                "turnoverRate": "0.1166",
                "regionName": "United States",
                "regionIsoCode": "US",
                "peTtm": "-1.2012",
                "preClose": "6.39",
                "fiftyTwoWkHigh": "13.97",
                "fiftyTwoWkLow": "0.5700",
                "open": "6.26",
                "high": "6.80",
                "low": "6.21",
                "vibrateRatio": "0.0923",
                "pprice": "6.64",
                "pchange": "-0.08",
                "pchRatio": "-0.0119"
            },
            "values": {
                "tickerId": 913254273,
                "change": "2.17",
                "changeRatio": "0.4769"
            }
        },
        {
            "ticker": {
                "tickerId": 950185318,
                "exchangeId": 96,
                "type": 2,
                "secType": [
                    61
                ],
                "regionId": 6,
                "currencyId": 247,
                "currencyCode": "USD",
                "name": "ELEVATION ONCOLO",
                "symbol": "ELEV",
                "disSymbol": "ELEV",
                "disExchangeCode": "NASDAQ",
                "exchangeCode": "NSQ",
                "listStatus": 1,
                "template": "stock",
                "tradeTime": "2021-08-20T20:00:00.000+0000",
                "status": "D",
                "close": "12.75",
                "change": "-0.17",
                "changeRatio": "-0.0132",
                "marketValue": "296126871",
                "volume": "10354",
                "turnoverRate": "0.0004",
                "regionName": "United States",
                "regionIsoCode": "US",
                "peTtm": "0",
                "preClose": "12.92",
                "fiftyTwoWkHigh": "16.22",
                "fiftyTwoWkLow": "7.71",
                "open": "12.79",
                "high": "12.79",
                "low": "12.37",
                "vibrateRatio": "0.0325",
                "pprice": "11.1401",
                "pchange": "-1.22",
                "pchRatio": "-0.0987"
            },
            "values": {
                "tickerId": 950185318,
                "change": "3.95",
                "changeRatio": "0.4489"
            }
        },
        {
            "ticker": {
                "tickerId": 913254183,
                "exchangeId": 10,
                "type": 2,
                "secType": [
                    61
                ],
                "regionId": 6,
                "currencyId": 247,
                "currencyCode": "USD",
                "name": "Nymox",
                "symbol": "NYMX",
                "disSymbol": "NYMX",
                "disExchangeCode": "NASDAQ",
                "exchangeCode": "NAS",
                "listStatus": 1,
                "template": "stock",
                "derivativeSupport": 1,
                "tradeTime": "2021-08-20T23:51:25.799+0000",
                "faTradeTime": "2021-08-20T23:51:25.799+0000",
                "status": "A",
                "close": "1.940",
                "change": "0.150",
                "changeRatio": "0.0838",
                "marketValue": "152699632",
                "volume": "240961",
                "turnoverRate": "0.0031",
                "regionName": "United States",
                "regionIsoCode": "US",
                "peTtm": "-11.9679",
                "preClose": "1.790",
                "fiftyTwoWkHigh": "3.500",
                "fiftyTwoWkLow": "1.252",
                "open": "1.760",
                "high": "1.950",
                "low": "1.760",
                "vibrateRatio": "0.1061",
                "pprice": "1.96",
                "pchange": "0.020",
                "pchRatio": "0.0103"
            },
            "values": {
                "tickerId": 913254183,
                "change": "0.600",
                "changeRatio": "0.4478"
            }
        },
        {
            "ticker": {
                "tickerId": 950177657,
                "exchangeId": 96,
                "type": 2,
                "secType": [
                    61
                ],
                "regionId": 6,
                "currencyId": 247,
                "currencyCode": "USD",
                "name": "MARAVAI LIFESCIENCES HOLDINGS, INC.",
                "symbol": "MRVI",
                "disSymbol": "MRVI",
                "disExchangeCode": "NASDAQ",
                "exchangeCode": "NSQ",
                "listStatus": 1,
                "template": "stock",
                "derivativeSupport": 1,
                "tradeTime": "2021-08-20T20:00:00.000+0000",
                "faTradeTime": "2021-08-20T20:00:11.992+0000",
                "status": "A",
                "close": "60.62",
                "change": "2.31",
                "changeRatio": "0.0396",
                "marketValue": "15630170476",
                "volume": "836012",
                "turnoverRate": "0.0032",
                "regionName": "United States",
                "regionIsoCode": "US",
                "peTtm": "147.1359",
                "preClose": "58.31",
                "fiftyTwoWkHigh": "60.17",
                "fiftyTwoWkLow": "23.62",
                "open": "58.75",
                "high": "60.93",
                "low": "58.49",
                "vibrateRatio": "0.0418",
                "pprice": "60.62",
                "pchange": "0.00",
                "pchRatio": "0.0000"
            },
            "values": {
                "tickerId": 950177657,
                "change": "18.62",
                "changeRatio": "0.4433"
            }
        },
        {
            "ticker": {
                "tickerId": 913253512,
                "exchangeId": 10,
                "type": 2,
                "secType": [
                    61
                ],
                "regionId": 6,
                "currencyId": 247,
                "currencyCode": "USD",
                "name": "Marathon Digital Holdings Inc",
                "symbol": "MARA",
                "disSymbol": "MARA",
                "disExchangeCode": "NASDAQ",
                "exchangeCode": "NAS",
                "listStatus": 1,
                "template": "stock",
                "derivativeSupport": 1,
                "tradeTime": "2021-08-20T23:59:38.129+0000",
                "faTradeTime": "2021-08-20T23:59:38.129+0000",
                "status": "A",
                "close": "35.26",
                "change": "3.45",
                "changeRatio": "0.1085",
                "marketValue": "3513099176",
                "volume": "15533243",
                "turnoverRate": "0.1559",
                "regionName": "United States",
                "regionIsoCode": "US",
                "peTtm": "58.1560",
                "preClose": "31.81",
                "fiftyTwoWkHigh": "57.75",
                "fiftyTwoWkLow": "1.480",
                "open": "32.57",
                "high": "36.18",
                "low": "32.37",
                "vibrateRatio": "0.1198",
                "pprice": "35.99",
                "pchange": "0.73",
                "pchRatio": "0.0207"
            },
            "values": {
                "tickerId": 913253512,
                "change": "10.62",
                "changeRatio": "0.4310"
            }
        },
        {
            "ticker": {
                "tickerId": 925302783,
                "exchangeId": 11,
                "type": 2,
                "secType": [
                    61
                ],
                "regionId": 6,
                "currencyId": 247,
                "currencyCode": "USD",
                "name": "Alpha Metallurgical Resources Inc",
                "symbol": "AMR",
                "disSymbol": "AMR",
                "disExchangeCode": "NYSE",
                "exchangeCode": "NYSE",
                "listStatus": 1,
                "template": "stock",
                "derivativeSupport": 1,
                "tradeTime": "2021-08-20T20:00:00.000+0000",
                "faTradeTime": "2021-08-20T20:00:13.235+0000",
                "status": "A",
                "close": "34.10",
                "change": "1.26",
                "changeRatio": "0.0384",
                "marketValue": "627450809",
                "volume": "128357",
                "turnoverRate": "0.0070",
                "regionName": "United States",
                "regionIsoCode": "US",
                "peTtm": "-43.1919",
                "preClose": "32.84",
                "fiftyTwoWkHigh": "37.14",
                "fiftyTwoWkLow": "3.830",
                "open": "32.53",
                "high": "35.16",
                "low": "32.26",
                "vibrateRatio": "0.0857",
                "pprice": "34.10",
                "pchange": "0.00",
                "pchRatio": "0.0000"
            },
            "values": {
                "tickerId": 925302783,
                "change": "10.24",
                "changeRatio": "0.4292"
            }
        },
        {
            "ticker": {
                "tickerId": 925293492,
                "exchangeId": 95,
                "type": 2,
                "secType": [
                    61
                ],
                "regionId": 6,
                "currencyId": 247,
                "currencyCode": "USD",
                "name": "Altimmune",
                "symbol": "ALT",
                "disSymbol": "ALT",
                "disExchangeCode": "NASDAQ",
                "exchangeCode": "NMS",
                "listStatus": 1,
                "template": "stock",
                "derivativeSupport": 1,
                "tradeTime": "2021-08-20T22:47:55.979+0000",
                "faTradeTime": "2021-08-20T22:47:55.979+0000",
                "status": "A",
                "close": "12.68",
                "change": "1.10",
                "changeRatio": "0.0950",
                "marketValue": "503470609",
                "volume": "1311803",
                "turnoverRate": "0.0330",
                "regionName": "United States",
                "regionIsoCode": "US",
                "peTtm": "-6.9982",
                "preClose": "11.58",
                "fiftyTwoWkHigh": "26.40",
                "fiftyTwoWkLow": "7.80",
                "open": "11.72",
                "high": "12.80",
                "low": "11.70",
                "vibrateRatio": "0.0950",
                "pprice": "12.68",
                "pchange": "0.00",
                "pchRatio": "0.0000"
            },
            "values": {
                "tickerId": 925293492,
                "change": "3.80",
                "changeRatio": "0.4279"
            }
        },
        {
            "ticker": {
                "tickerId": 950158958,
                "exchangeId": 11,
                "type": 2,
                "secType": [
                    61
                ],
                "regionId": 6,
                "currencyId": 247,
                "currencyCode": "USD",
                "name": "Albertsons Companies, Inc.",
                "symbol": "ACI",
                "disSymbol": "ACI",
                "disExchangeCode": "NYSE",
                "exchangeCode": "NYSE",
                "listStatus": 1,
                "template": "stock",
                "derivativeSupport": 1,
                "tradeTime": "2021-08-20T23:08:23.043+0000",
                "faTradeTime": "2021-08-20T23:08:23.043+0000",
                "status": "A",
                "close": "28.86",
                "change": "0.19",
                "changeRatio": "0.0066",
                "marketValue": "13824712091",
                "volume": "757135",
                "turnoverRate": "0.0016",
                "regionName": "United States",
                "regionIsoCode": "US",
                "peTtm": "23.6441",
                "preClose": "28.67",
                "fiftyTwoWkHigh": "30.42",
                "fiftyTwoWkLow": "12.91",
                "open": "28.75",
                "high": "29.09",
                "low": "28.66",
                "vibrateRatio": "0.0150",
                "pprice": "28.90",
                "pchange": "0.04",
                "pchRatio": "0.0014"
            },
            "values": {
                "tickerId": 950158958,
                "change": "8.62",
                "changeRatio": "0.4259"
            }
        },
        {
            "ticker": {
                "tickerId": 913323870,
                "exchangeId": 10,
                "type": 2,
                "secType": [
                    61
                ],
                "regionId": 6,
                "currencyId": 247,
                "currencyCode": "USD",
                "name": "Support.com",
                "symbol": "SPRT",
                "disSymbol": "SPRT",
                "disExchangeCode": "NASDAQ",
                "exchangeCode": "NAS",
                "listStatus": 1,
                "template": "stock",
                "derivativeSupport": 1,
                "tradeTime": "2021-08-20T23:59:56.695+0000",
                "faTradeTime": "2021-08-20T23:59:56.695+0000",
                "status": "A",
                "close": "8.81",
                "change": "0.04",
                "changeRatio": "0.0046",
                "marketValue": "213535687",
                "volume": "29067513",
                "turnoverRate": "1.1993",
                "regionName": "United States",
                "regionIsoCode": "US",
                "peTtm": "-93.1290",
                "preClose": "8.77",
                "fiftyTwoWkHigh": "10.88",
                "fiftyTwoWkLow": "1.620",
                "open": "9.29",
                "high": "10.44",
                "low": "8.56",
                "vibrateRatio": "0.2144",
                "pprice": "8.90",
                "pchange": "0.09",
                "pchRatio": "0.0102"
            },
            "values": {
                "tickerId": 913323870,
                "change": "2.63",
                "changeRatio": "0.4256"
            }
        },
        {
            "ticker": {
                "tickerId": 913430557,
                "exchangeId": 10,
                "type": 2,
                "secType": [
                    61
                ],
                "regionId": 6,
                "currencyId": 247,
                "currencyCode": "USD",
                "name": "SCWorx Corp",
                "symbol": "WORX",
                "disSymbol": "WORX",
                "disExchangeCode": "NASDAQ",
                "exchangeCode": "NAS",
                "listStatus": 1,
                "template": "stock",
                "tradeTime": "2021-08-20T23:58:20.173+0000",
                "faTradeTime": "2021-08-20T23:58:20.173+0000",
                "status": "A",
                "close": "2.750",
                "change": "-0.400",
                "changeRatio": "-0.1270",
                "marketValue": "28974115",
                "volume": "1557215",
                "turnoverRate": "0.1478",
                "regionName": "United States",
                "regionIsoCode": "US",
                "peTtm": "-3.6696",
                "preClose": "3.150",
                "fiftyTwoWkHigh": "5.00",
                "fiftyTwoWkLow": "1.000",
                "open": "3.250",
                "high": "3.250",
                "low": "2.720",
                "vibrateRatio": "0.1619",
                "pprice": "2.76",
                "pchange": "0.010",
                "pchRatio": "0.0036"
            },
            "values": {
                "tickerId": 913430557,
                "change": "0.820",
                "changeRatio": "0.4249"
            }
        },
        {
            "ticker": {
                "tickerId": 913256052,
                "exchangeId": 95,
                "type": 2,
                "secType": [
                    61
                ],
                "regionId": 6,
                "currencyId": 247,
                "currencyCode": "USD",
                "name": "CPI Card Group",
                "symbol": "PMTS",
                "disSymbol": "PMTS",
                "disExchangeCode": "NASDAQ",
                "exchangeCode": "NMS",
                "listStatus": 1,
                "template": "stock",
                "tradeTime": "2021-08-20T20:00:00.000+0000",
                "faTradeTime": "2021-08-20T11:08:28.171+0000",
                "status": "D",
                "close": "22.52",
                "change": "-0.13",
                "changeRatio": "-0.0057",
                "marketValue": "253102144",
                "volume": "46360",
                "turnoverRate": "0.0041",
                "regionName": "United States",
                "regionIsoCode": "US",
                "peTtm": "11.8178",
                "preClose": "22.65",
                "fiftyTwoWkHigh": "27.68",
                "fiftyTwoWkLow": "1.550",
                "open": "22.33",
                "high": "23.01",
                "low": "21.60",
                "vibrateRatio": "0.0621",
                "pprice": "22.50",
                "pchange": "-0.15",
                "pchRatio": "-0.0066"
            },
            "values": {
                "tickerId": 913256052,
                "change": "6.62",
                "changeRatio": "0.4164"
            }
        },
        {
            "ticker": {
                "tickerId": 950136125,
                "exchangeId": 10,
                "type": 2,
                "secType": [
                    61
                ],
                "regionId": 6,
                "currencyId": 247,
                "currencyCode": "USD",
                "name": "CHINA LIBERAL EDUCATION",
                "symbol": "CLEU",
                "disSymbol": "CLEU",
                "disExchangeCode": "NASDAQ",
                "exchangeCode": "NAS",
                "listStatus": 1,
                "template": "stock",
                "tradeTime": "2021-08-20T23:12:00.442+0000",
                "faTradeTime": "2021-08-20T23:12:00.442+0000",
                "status": "A",
                "close": "2.600",
                "change": "0.060",
                "changeRatio": "0.0236",
                "marketValue": "32066665",
                "volume": "2535007",
                "turnoverRate": "0.2055",
                "regionName": "United States",
                "regionIsoCode": "US",
                "peTtm": "13.8004",
                "preClose": "2.540",
                "fiftyTwoWkHigh": "10.46",
                "fiftyTwoWkLow": "1.580",
                "open": "2.557",
                "high": "2.700",
                "low": "2.350",
                "vibrateRatio": "0.1378",
                "pprice": "2.59",
                "pchange": "-0.010",
                "pchRatio": "-0.0038"
            },
            "values": {
                "tickerId": 950136125,
                "change": "0.750",
                "changeRatio": "0.4054"
            }
        },
        {
            "ticker": {
                "tickerId": 950145229,
                "exchangeId": 95,
                "type": 2,
                "secType": [
                    62
                ],
                "regionId": 6,
                "currencyId": 247,
                "currencyCode": "USD",
                "name": "Canaan Inc.",
                "symbol": "CAN",
                "disSymbol": "CAN",
                "disExchangeCode": "NASDAQ",
                "exchangeCode": "NMS",
                "listStatus": 1,
                "template": "stock",
                "derivativeSupport": 1,
                "tradeTime": "2021-08-20T23:59:53.360+0000",
                "faTradeTime": "2021-08-20T23:59:53.360+0000",
                "status": "A",
                "close": "8.06",
                "change": "0.30",
                "changeRatio": "0.0387",
                "marketValue": "1383420116",
                "volume": "6418171",
                "turnoverRate": "0.0374",
                "regionName": "United States",
                "regionIsoCode": "US",
                "peTtm": "-47.4956",
                "preClose": "7.76",
                "fiftyTwoWkHigh": "39.10",
                "fiftyTwoWkLow": "1.800",
                "open": "8.01",
                "high": "8.60",
                "low": "7.97",
                "vibrateRatio": "0.0812",
                "pprice": "8.26",
                "pchange": "0.20",
                "pchRatio": "0.0248"
            },
            "values": {
                "tickerId": 950145229,
                "change": "2.30",
                "changeRatio": "0.3993"
            }
        },
        {
            "ticker": {
                "tickerId": 925402184,
                "exchangeId": 10,
                "type": 2,
                "secType": [
                    61
                ],
                "regionId": 6,
                "currencyId": 247,
                "currencyCode": "USD",
                "name": "Adial",
                "symbol": "ADIL",
                "disSymbol": "ADIL",
                "disExchangeCode": "NASDAQ",
                "exchangeCode": "NAS",
                "listStatus": 1,
                "template": "stock",
                "tradeTime": "2021-08-20T23:39:03.657+0000",
                "faTradeTime": "2021-08-20T23:39:03.657+0000",
                "status": "A",
                "close": "3.340",
                "change": "0.220",
                "changeRatio": "0.0705",
                "marketValue": "67795841",
                "volume": "1498588",
                "turnoverRate": "0.0738",
                "regionName": "United States",
                "regionIsoCode": "US",
                "peTtm": "-3.2054",
                "preClose": "3.120",
                "fiftyTwoWkHigh": "4.000",
                "fiftyTwoWkLow": "1.140",
                "open": "3.130",
                "high": "3.500",
                "low": "3.100",
                "vibrateRatio": "0.1250",
                "pprice": "3.36",
                "pchange": "0.020",
                "pchRatio": "0.0060"
            },
            "values": {
                "tickerId": 925402184,
                "change": "0.950",
                "changeRatio": "0.3975"
            }
        },
        {
            "ticker": {
                "tickerId": 925337792,
                "exchangeId": 10,
                "type": 2,
                "secType": [
                    61
                ],
                "regionId": 6,
                "currencyId": 247,
                "currencyCode": "USD",
                "name": "HIVE",
                "symbol": "HVBT",
                "disSymbol": "HVBT",
                "disExchangeCode": "NASDAQ",
                "exchangeCode": "NAS",
                "listStatus": 1,
                "template": "stock",
                "tradeTime": "2021-08-20T23:59:12.229+0000",
                "faTradeTime": "2021-08-20T23:59:12.229+0000",
                "status": "A",
                "close": "3.040",
                "change": "0.090",
                "changeRatio": "0.0305",
                "marketValue": "1157821571",
                "volume": "4666529",
                "turnoverRate": "0.0123",
                "regionName": "United States",
                "regionIsoCode": "US",
                "peTtm": "37.5773",
                "preClose": "2.950",
                "fiftyTwoWkHigh": "5.75",
                "fiftyTwoWkLow": "0.2250",
                "open": "3.020",
                "high": "3.150",
                "low": "2.930",
                "vibrateRatio": "0.0746",
                "pprice": "3.26",
                "pchange": "0.220",
                "pchRatio": "0.0724"
            },
            "values": {
                "tickerId": 925337792,
                "change": "0.860",
                "changeRatio": "0.3945"
            }
        },
        {
            "ticker": {
                "tickerId": 913324109,
                "exchangeId": 95,
                "type": 2,
                "secType": [
                    61
                ],
                "regionId": 6,
                "currencyId": 247,
                "currencyCode": "USD",
                "name": "Ever Glory Intl",
                "symbol": "EVK",
                "disSymbol": "EVK",
                "disExchangeCode": "NASDAQ",
                "exchangeCode": "NMS",
                "listStatus": 1,
                "template": "stock",
                "tradeTime": "2021-08-20T22:41:59.882+0000",
                "faTradeTime": "2021-08-20T22:41:59.882+0000",
                "status": "A",
                "close": "3.010",
                "change": "0.040",
                "changeRatio": "0.0135",
                "marketValue": "44580086",
                "volume": "119587",
                "turnoverRate": "0.0081",
                "regionName": "United States",
                "regionIsoCode": "US",
                "peTtm": "9.2701",
                "preClose": "2.970",
                "fiftyTwoWkHigh": "8.30",
                "fiftyTwoWkLow": "0.8012",
                "open": "2.884",
                "high": "3.090",
                "low": "2.884",
                "vibrateRatio": "0.0695",
                "pprice": "3.01",
                "pchange": "0.000",
                "pchRatio": "0.0000"
            },
            "values": {
                "tickerId": 913324109,
                "change": "0.850",
                "changeRatio": "0.3935"
            }
        }
    ]
}